[{"word":"孙颖莎冠军","word_scheme":"#孙颖莎冠军#","num":2320474,"icon_desc":"新","rank":0,"category":"体育","description":"祝贺孙颖莎！"},{"word":"桂林旅游累计亏损10亿","word_scheme":"#桂林旅游累计亏损10亿#","num":964647,"icon_desc":"热","rank":1,"category":"社会","description":"这并非桂林旅游公司首次面临亏损，从近几年财报来看，桂林旅游公司自2020年以来已累计亏损近10亿元，其中2020—2022年连续三年亏损，2023年短暂盈利后，2024年再度陷入亏损。"},{"word":"何以中国走进福建","word_scheme":"#何以中国走进福建#","num":810570,"rank":2,"category":"社会","description":"福建南平建瓯，是古建州治所地。千年建州，食全酒美，这里的美食有500多种。游客来了，可以品尝到“一城百味”，感受“建州味道”，不虚此行。"},{"word":"31岁男星黄正杰去世","word_scheme":"#31岁男星黄正杰去世#","num":808467,"icon_desc":"新","rank":3,"category":"社会","description":"突传讣告！33岁男星黄正杰去世，两天前还曾录制跳舞视频，母亲透露死因及遗言"},{"word":"林诗栋vs雨果","word_scheme":"#林诗栋vs雨果#","num":768803,"icon_desc":"新","rank":4,"category":"体育","description":"男单决赛，林诗栋vs雨果"},{"word":"孙颖莎vs蒯曼","word_scheme":"#孙颖莎vs蒯曼#","num":725295,"rank":5,"category":"体育","description":"2025年澳门世界杯女单决赛，孙颖莎vs蒯曼。为运动员加油！"},{"word":"饺子在美国身价涨到一美元一个","word_scheme":"#饺子在美国身价涨到一美元一个#","num":588580,"icon_desc":"新","rank":6,"category":"社会","description":"近日，众多网友在社交媒体上晒出美国中餐馆的涨价菜单，引发广泛关注"},{"word":"女子出现在热播剧中自己毫不知情","word_scheme":"#女子出现在热播剧中自己毫不知情#","num":494532,"rank":7,"category":"社会","description":"近日，一位在深圳工作的女子称，她发现在最新的热播剧中，有一段去年和朋友在维港摩天轮下游玩拍照的镜头，大约不到2秒，还配了一句台词，而自己对此并不知情。"},{"word":"苹果回应iPhone电池健康80和100的区别","word_scheme":"#苹果回应iPhone电池健康80和100的区别#","num":359132,"icon_desc":"新","rank":8,"category":"科技","description":"苹果工作人员回应：100电池容量就是新电池的状态；80可以理解为满电情况下，实际上电量储蓄是原来80%。"},{"word":"孙颖莎蒯曼女单决赛对战","word_scheme":"#孙颖莎蒯曼女单决赛对战#","num":358663,"rank":9,"category":"体育","description":"一起为国乒加油！"},{"word":"鹿晗 关晓彤","word_scheme":"鹿晗 关晓彤","num":13959439,"icon_desc":"爆","rank":10,"category":"明星","description":""},{"word":"赵露思 范思哲","word_scheme":"赵露思 范思哲","num":352358,"icon_desc":"新","flag_desc":"盛典","rank":11,"category":"","description":""},{"word":"断网了这竟然是沙溢","word_scheme":"断网了这竟然是沙溢","num":349614,"icon_desc":"热","rank":12,"category":"综艺","description":""},{"word":"白鹿直播","word_scheme":"白鹿直播","num":349610,"icon_desc":"新","rank":13,"category":"","description":""},{"word":"孙颖莎回应世界杯卫冕","word_scheme":"#孙颖莎回应世界杯卫冕#","num":307204,"icon_desc":"新","rank":14,"category":"体育","description":""},{"word":"等关晓彤发博","word_scheme":"#等关晓彤发博#","num":301362,"icon_desc":"热","rank":15,"category":"明星","description":""},{"word":"九重紫宋墨篇开局就杀疯了","word_scheme":"九重紫宋墨篇开局就杀疯了","num":266609,"icon_desc":"新","flag_desc":"剧集","rank":16,"category":"","description":""},{"word":"小尼魔术挑战大变汽车","word_scheme":"#小尼魔术挑战大变汽车#","num":266283,"icon_desc":"新","rank":17,"category":"社会","description":"看小尼如何大变汽车！"},{"word":"请给保洁员一个休息空间","word_scheme":"#请给保洁员一个休息空间#","num":265646,"icon_desc":"新","rank":18,"category":"社会","description":"华东政法大学学生江亦心，通过“校长信箱”建议增设设施完善的保洁休息室。很快，学校就在宿舍区开辟了一间保洁员休息室↓↓"},{"word":"榴莲为什么这么好吃","word_scheme":"榴莲为什么这么好吃","num":264756,"icon_desc":"新","rank":19,"category":"","description":""},{"word":"邓超发文让高瀚宇退圈","word_scheme":"#邓超发文让高瀚宇退圈#","num":263719,"icon_desc":"热","rank":20,"category":"明星","description":""},{"word":"迪丽热巴发型师 方可","word_scheme":"迪丽热巴发型师 方可","num":262844,"rank":21,"category":"","description":""},{"word":"刘国正说邱贻可现在非常舒心","word_scheme":"#刘国正说邱贻可现在非常舒心#","num":262661,"icon_desc":"新","rank":22,"category":"社会","description":"澳门乒乓球世界杯女单决赛，@孙颖莎对阵蒯曼@kuaiman0207，两位都是邱贻可的得意弟子，解说嘉宾@刘国正说道：邱指导现在是非常舒心的，负责把球捡好就行了。"},{"word":"李一桐唇钻","word_scheme":"#李一桐唇钻#","num":260052,"icon_desc":"新","rank":23,"category":"明星-内地","description":""},{"word":"美媒承认中国手里有张王牌","word_scheme":"#美媒承认中国手里有张王牌#","num":257622,"rank":24,"category":"社会","description":""},{"word":"刘涛为妈祖献寿桃","word_scheme":"#刘涛为妈祖献寿桃#","num":252677,"rank":25,"category":"明星-内地","description":"4月20日，农历三月廿三妈祖诞辰日。据悉，今年是妈祖诞辰1065周年。19日晚，演员@刘涛tamia现身莆田湄洲岛，为妈祖献上了寿桃。"},{"word":"深圳女生回应被拍进热播剧","word_scheme":"#深圳女生回应被拍进热播剧#","num":227032,"icon_desc":"新","rank":26,"category":"社会","description":"近日，一位在深圳工作的女子称，她发现在最新的热播剧中，有一段去年和朋友在维港摩天轮下游玩拍照的镜头，大约不到2秒，还配了一句台词，而自己对此并不知情。"},{"word":"华晨宇音乐节","word_scheme":"华晨宇音乐节","num":218027,"icon_desc":"新","flag_desc":"演出","rank":27,"category":"","description":""},{"word":"五月天白敬亭合唱任性","word_scheme":"五月天白敬亭合唱任性","num":213374,"icon_desc":"新","flag_desc":"演出","rank":28,"category":"","description":""},{"word":"佛山电翰回应买迈巴赫","word_scheme":"#佛山电翰回应买迈巴赫#","num":212730,"icon_desc":"新","rank":29,"category":"社会","description":"近日，网红“佛山电翰”因接受媒体采访再次引发关注，4月20日，“佛山电翰”发视频回应质疑，“佛山电翰”表示做直播差不多2年才火，买车了大方说出来感觉没什么问题，谁努力不是为了可以过好生活，直播基本都是自然流，这2年最大的收获还是整体认知的提升。"},{"word":"高中生打破黄雨婷保持的世界纪录","word_scheme":"#高中生打破黄雨婷保持的世界纪录#","num":212514,"rank":30,"category":"社会","description":""},{"word":"ITTF","word_scheme":"ITTF","num":201874,"icon_desc":"新","rank":31,"category":"","description":""},{"word":"孙颖莎4比0蒯曼","word_scheme":"#孙颖莎4比0蒯曼#","num":196141,"icon_desc":"新","rank":32,"category":"社会","description":"4月20日，澳门乒乓球世界杯女单决赛中，@孙颖莎4比0战胜蒯曼@kuaiman0207，获得冠军！继续加油！"},{"word":"孙颖莎说发挥比想象中好","word_scheme":"#孙颖莎说发挥比想象中好#","num":195124,"icon_desc":"新","rank":33,"category":"明星","description":"4月20日，孙颖莎4比0战胜蒯曼，夺得澳门世界杯女单冠军。"},{"word":"美高官爆料五角大楼已完全崩溃","word_scheme":"#美高官爆料五角大楼已完全崩溃#","num":191696,"rank":34,"category":"时事","description":""},{"word":"女生婚礼前特意做美甲婚戒卡手指上","word_scheme":"#女生婚礼前特意做美甲婚戒卡手指上#","num":187785,"rank":35,"category":"社会","description":"4月18日，广东。女生婚礼前，特意去做了好看的美甲迎接婚礼，结果做好后，因为贴了东西导致钻戒卡在了手指上，怎么也取不下来……"},{"word":"乒乓球世界杯","word_scheme":"乒乓球世界杯","num":171045,"icon_desc":"新","rank":36,"category":"体育","description":"11月6日-10日，团体世界杯即将在日本东京拉开战幕。本次团体世界杯采用邀请制，男女团各有12支参赛队伍。根据入围规则，东道主日本队自动获得一个参赛席位。在最新的洲际锦标赛中获得团体冠军的队伍、以及泛美洲锦标赛的亚军均受邀参赛。其余5个参赛席位根据2018团体世乒赛成绩决定。"},{"word":"爸爸找到失散女儿第一句话是对不起","word_scheme":"#爸爸找到失散女儿第一句话是对不起#","num":154436,"icon_desc":"新","rank":37,"category":"社会","description":"4月20日，贵州。2006年10月19号，陈生梨带着三岁零四个月的女儿陈杨梅在广场上摆摊唱歌，一个没注意，女儿竟丢了，从此陈生梨就踏上了寻女之路。19年来他边找孩子边摆摊卖棉花糖，开坏了两辆面包车，今年4月份，棉花糖爸爸终于等来了好消息！"},{"word":"这些星座请做好脱单的准备","word_scheme":"#这些星座请做好脱单的准备#","num":149526,"icon_desc":"新","rank":38,"category":"星座","description":""},{"word":"宋祖儿任嘉伦吻戏","word_scheme":"宋祖儿任嘉伦吻戏","num":148245,"icon_desc":"新","flag_desc":"剧集","rank":39,"category":"","description":""},{"word":"范思哲活动阵容","word_scheme":"#范思哲活动阵容#","num":147955,"rank":40,"category":"电影","description":""},{"word":"COA8总决赛抽签","word_scheme":"#COA8总决赛抽签#","num":147919,"icon_desc":"新","rank":41,"category":"","description":""},{"word":"孟美岐七年变的是时间不变的是热爱","word_scheme":"孟美岐七年变的是时间不变的是热爱","num":145250,"icon_desc":"新","rank":42,"category":"","description":""},{"word":"郑秀妍在兵马俑请粉丝喝饮料","word_scheme":"#郑秀妍在兵马俑请粉丝喝饮料#","num":136766,"icon_desc":"新","rank":43,"category":"明星","description":"4月19日，陕西西安。网友在兵马俑偶遇@Sy__Jessica郑秀妍，郑秀妍还热情地请粉丝喝饮料。粉丝：希望姐姐和爸爸妈妈在西安玩得开心！"},{"word":"第一次看悬疑剧冷到我想搓手","word_scheme":"第一次看悬疑剧冷到我想搓手","num":135936,"icon_desc":"新","flag_desc":"剧集","rank":44,"category":"","description":""},{"word":"韦世豪头球破门","word_scheme":"#韦世豪头球破门#","num":132505,"icon_desc":"新","rank":45,"category":"体育","description":"武汉三镇vs沧州雄狮的中超联赛，韦世豪头球破门"},{"word":"zb1二巡","word_scheme":"zb1二巡","num":132146,"icon_desc":"新","flag_desc":"演出","rank":46,"category":"","description":""},{"word":"迪丽热巴金色纱裙","word_scheme":"#迪丽热巴金色纱裙#","num":131939,"rank":47,"category":"明星","description":"迪丽热巴金色纱裙"},{"word":"张峻豪范思哲大片","word_scheme":"张峻豪范思哲大片","num":130597,"flag_desc":"盛典","rank":48,"category":"","description":""},{"word":"闪耀暖暖","word_scheme":"闪耀暖暖","num":129049,"icon_desc":"新","rank":49,"category":"游戏","description":"2025年4月20日19:30，全体起立——【版本前瞻极速版】恭迎黑月光回归，看她如何夺走一切光明！"}]