[{"word":"曹骏出场","word_scheme":"曹骏出场","num":1113004,"icon_desc":"热","flag_desc":"剧集","rank":0,"category":"","description":""},{"word":"猿辅导回应武汉员工事件","word_scheme":"#猿辅导回应武汉员工事件#","num":932880,"icon_desc":"新","rank":1,"category":"科技","description":"25日上午，猿辅导就日前武汉公司员工李某某意外离世事件作出回应。"},{"word":"第一视角看神20发射多震撼","word_scheme":"#第一视角看神20发射多震撼#","num":914734,"rank":2,"category":"社会","description":"4月24日下午，搭载神舟二十号载人飞船的长征二号F遥二十运载火箭在酒泉卫星发射中心点火发射。蓝天为背景，大漠作底衬，画面震撼又美好。伴随@卡布叻_周深的歌声，一起直击神二十飞天瞬间！"},{"word":"以太平之名 赴星河之约","num":914617,"icon_desc":"商","rank":2,"category":"科技","description":"携手航天，共筑未来！2025年4月24日，在第十个\"中国航天日\"到来之际，太平人寿与中国火箭正式达成品牌联名合作。双方将以航天精神为引领，共同开启守护探索的新篇章！"},{"word":"猿辅导老师猝死在公司人社局介入","word_scheme":"#猿辅导老师猝死在公司人社局介入#","num":914525,"icon_desc":"新","rank":3,"category":"社会","description":"猿辅导武汉公司一名年轻老师在办公室猝死，引发关注。目前，武汉市人社局东湖新技术开发区分局已介入调查。"},{"word":"猿辅导前员工称1人带400个学生","word_scheme":"#猿辅导前员工称1人带400个学生#","num":914197,"rank":4,"category":"社会","description":"去年从猿辅导离职的员工称，几乎每天加班，“我一个人负责400个学生，课后要答疑，卖课过程要录音。公司随即抽查录音，并约谈你哪里做得不好。每天很焦虑。”"},{"word":"黄子韬卫生巾公司招聘大专起投","word_scheme":"#黄子韬卫生巾公司招聘大专起投#","num":784522,"icon_desc":"热","rank":5,"category":"社会","description":""},{"word":"不良人集结WAW漫展开票","num":653832,"icon_desc":"荐","rank":5,"category":"动漫","description":"微博游戏动漫展心愿能量值已超标，动漫特邀嘉宾微博空降中！"},{"word":"新疆下井救人00后女辅警破格晋升","word_scheme":"#新疆下井救人00后女辅警破格晋升#","num":473353,"icon_desc":"暖","rank":6,"category":"社会","description":"4月24日，新疆洛浦县公安局举行优秀警务辅助人员晋升层级暨授衔仪式。报道显示，经局党委研究，决定对主动请缨下井救人的布帕太姆·阿布杜喀迪尔破格从七级晋升至五级，同时对其余优秀辅警进行授衔。"},{"word":"周杰伦年纪越大希望减少工作量","word_scheme":"#周杰伦年纪越大希望减少工作量#","num":460624,"icon_desc":"新","rank":7,"category":"明星-港台","description":""},{"word":"白月光沉香杀回来了","word_scheme":"#白月光沉香杀回来了#","num":367903,"icon_desc":"新","flag_desc":"剧集","rank":8,"category":"社会","description":"这就是白月光的杀伤力啊！"},{"word":"莫兰特受伤","word_scheme":"莫兰特受伤","num":290104,"icon_desc":"新","rank":9,"category":"体育","description":"NBA季后赛，雷霆vs灰熊，莫兰特重摔在地受伤。"},{"word":"赵露思下车动作","word_scheme":"#赵露思下车动作#","num":278661,"icon_desc":"新","rank":10,"category":"明星-内地","description":""},{"word":"姐姐回应男子被打20个月后死亡","word_scheme":"#姐姐回应男子被打20个月后死亡#","num":268430,"rank":11,"category":"社会","description":"近日，广东陆丰王女士向记者反映，弟弟王嘉禧在2018年被两男子当街殴打，造成左侧偏瘫，后经救治仍没有好转，于2020年6月不幸去世，年仅27岁。"},{"word":"无忧渡 超点","word_scheme":"无忧渡 超点","num":259738,"icon_desc":"新","flag_desc":"剧集","rank":12,"category":"","description":""},{"word":"老外说是朱一龙的bigfan","word_scheme":"#老外说是朱一龙的bigfan#","num":230988,"icon_desc":"新","rank":13,"category":"社会","description":"“扬帆出海”的中国电影打动海外观众！"},{"word":"火锅险淋小孩老板强忍烫伤不松手","word_scheme":"#火锅险淋小孩老板强忍烫伤不松手#","num":220758,"icon_desc":"新","rank":14,"category":"社会","description":"4月18日，成都。火锅店老板端滚烫的火锅被小朋友冲撞，当即强忍烫伤疼痛没有松手。"},{"word":"中国航天6次太空会师666","word_scheme":"#中国航天6次太空会师666#","num":214647,"rank":15,"category":"社会","description":""},{"word":"邓家佳喜剧纯元回来了","word_scheme":"邓家佳喜剧纯元回来了","num":206345,"icon_desc":"新","flag_desc":"电影","rank":16,"category":"","description":""},{"word":"讨好性礼貌","word_scheme":"讨好性礼貌","num":204588,"icon_desc":"新","rank":17,"category":"","description":""},{"word":"胡兵54岁的成长告白","word_scheme":"#胡兵54岁的成长告白#","num":204055,"icon_desc":"新","rank":18,"category":"时尚","description":""},{"word":"王者荣耀杨玉环皮肤优化有哪些亮点","word_scheme":"王者荣耀杨玉环皮肤优化有哪些亮点","num":201172,"icon_desc":"新","rank":19,"category":"","description":""},{"word":"猿辅导老师猝死家属发声","word_scheme":"#猿辅导老师猝死家属发声#","num":199959,"rank":20,"category":"社会","description":"死者家属称，他父亲早年去世，原定5月2日结婚，“家里人现在哭得说不成话。”"},{"word":"尊界S800内饰太尊了","word_scheme":"#尊界S800内饰太尊了#","num":197730,"icon_desc":"新","rank":21,"category":"汽车","description":"千呼万唤始出来，尊界S800的内饰今天正式公布。不得不说，#尊界S800内饰太尊了#！但与传统豪华，甚至是超豪品牌不同的是，尊界对奢华的演绎"},{"word":"原来这才算穿的干净","word_scheme":"#原来这才算穿的干净#","num":195772,"icon_desc":"新","rank":22,"category":"搞笑","description":""},{"word":"网红彩虹夫妇宣布停播","word_scheme":"#网红彩虹夫妇宣布停播#","num":194232,"icon_desc":"热","rank":23,"category":"财经","description":""},{"word":"谢霆锋发文感谢王嘉尔","word_scheme":"谢霆锋发文感谢王嘉尔","num":192949,"icon_desc":"新","flag_desc":"演出","rank":24,"category":"音乐","description":""},{"word":"建议把睡觉当作一天的开始","word_scheme":"#建议把睡觉当作一天的开始#","num":190623,"icon_desc":"新","rank":25,"category":"科普","description":"子时，也就是晚上11点~次日凌晨1点，是一天之中阴气最盛、阳气初生的时段，胆气也在此时开始升发。凡五脏六腑皆以气机通顺为要，子时睡好对一天至关重要，休息好了，第二天才能头脑清醒。"},{"word":"唐国强上优酷节目感谢哔哩哔哩","word_scheme":"唐国强上优酷节目感谢哔哩哔哩","num":189644,"icon_desc":"新","rank":26,"category":"","description":""},{"word":"10岁男童被生母继父虐死案庭审延期","word_scheme":"#10岁男童被生母继父虐死案庭审延期#","num":188482,"icon_desc":"新","rank":27,"category":"社会","description":""},{"word":"肖战上海","word_scheme":"#肖战上海#","num":185664,"rank":28,"category":"明星","description":"肖战上海，祝小赞工作顺顺利利！"},{"word":"朱正廷摇人抢labubu","word_scheme":"#朱正廷摇人抢labubu#","num":184582,"icon_desc":"新","rank":29,"category":"明星","description":"朱正廷：摇了好多人一个都没抢到！离谱🙃大家都不睡觉的嘛​​​"},{"word":"美官员承认误判中方反应","word_scheme":"#美官员承认误判中方反应#","num":183201,"rank":30,"category":"社会","description":""},{"word":"唐国强 我为什么不能参加这样的节目","word_scheme":"唐国强 我为什么不能参加这样的节目","num":180891,"icon_desc":"新","flag_desc":"综艺","rank":31,"category":"","description":""},{"word":"感觉她上的才是真大学","word_scheme":"感觉她上的才是真大学","num":172039,"icon_desc":"新","rank":32,"category":"","description":""},{"word":"快船vs掘金","word_scheme":"#快船vs掘金#","num":157842,"icon_desc":"新","rank":33,"category":"体育","description":"NBA季后赛，快船vs掘金。"},{"word":"李现官宣新身份","word_scheme":"#李现官宣新身份#","num":155174,"icon_desc":"新","rank":34,"category":"明星","description":""},{"word":"丁真被刘涛说眼里没感情","word_scheme":"#丁真被刘涛说眼里没感情#","num":153997,"icon_desc":"新","flag_desc":"综艺","rank":35,"category":"综艺-内地综艺","description":"《无限超越班》丁真被刘涛说眼里没感情！"},{"word":"老人扶梯上摔倒兵哥哥飞跃救人","word_scheme":"#老人扶梯上摔倒兵哥哥飞跃救人#","num":151205,"icon_desc":"暖","rank":36,"category":"社会","description":"在四川成都天府广场地铁口，担负执勤任务的武警官兵发现扶梯上两名老人站立不稳摔倒"},{"word":"梁博新专","word_scheme":"梁博新专","num":150030,"icon_desc":"新","flag_desc":"音乐","rank":37,"category":"明星-内地","description":""},{"word":"下周五一假期","word_scheme":"#下周五一假期#","num":137339,"icon_desc":"新","rank":38,"category":"社会","description":""},{"word":"英国将首次公布外国罪犯国籍","word_scheme":"英国将首次公布外国罪犯国籍","num":136547,"icon_desc":"新","rank":39,"category":"社会","description":"英国第四频道4月23日报道。居住在英国的外国罪犯的国籍将首次公布。内政部表示，他们希望公众更好地了解罪犯来自哪里。"},{"word":"菲方非法驻留破坏铁线礁生态","word_scheme":"#菲方非法驻留破坏铁线礁生态#","num":136426,"icon_desc":"新","rank":40,"category":"社会","description":"铁线礁海域发现有菲律宾等外方渔船未经许可非法开展捕捞作业，菲律宾在我中业岛上非法开展施工建设，相关调查站位发现有渔线、渔网、塑料包装、铁筒、玻璃瓶等人为弃置物，部分带有菲律宾文、部分带有产自菲律宾标识。"},{"word":"特朗普称美国若不买加拿大将不存在","word_scheme":"#特朗普称美国若不买加拿大将不存在#","num":134953,"rank":41,"category":"社会","description":""},{"word":"北京国际电影节闭幕式阵容官宣","word_scheme":"#北京国际电影节闭幕式阵容官宣#","num":130793,"icon_desc":"新","flag_desc":"盛典","rank":42,"category":"社会","description":"第十五届@北京国际电影节闭幕式首轮阵容官宣：陈佩斯、葛优、@摩登兄弟刘宇宁、@唐国强、@小柯、@岳红的家、@朱时茂等将一同见证光影闪耀时刻。4月26日，期待“天坛奖”奖项揭晓！#相约北影节#"},{"word":"金条供不应求","word_scheme":"#金条供不应求#","num":129130,"rank":43,"category":"财经","description":"购买金条需要交保证金，除了金价的剧烈波动以外，还跟金条的供不应求有关。在深圳水贝的一个专门批发投资金条的店铺内，人头攒动，不少柜台的金条已经被抢购一空。"},{"word":"陈都灵杂志","word_scheme":"陈都灵杂志","num":128913,"icon_desc":"新","flag_desc":"剧集","rank":44,"category":"","description":""},{"word":"乘风2025三公歌单","word_scheme":"#乘风2025三公歌单#","num":128639,"icon_desc":"新","flag_desc":"综艺","rank":45,"category":"综艺","description":"《乘风2025》第三场公演歌单揭晓"},{"word":"Wendy签约新公司","word_scheme":"#Wendy签约新公司#","num":127787,"icon_desc":"新","rank":46,"category":"明星-日韩","description":"据iMBC娱乐独家报道，Wendy近日与ASND签订了专属合约。"},{"word":"张继科夸马琳不是人是神","word_scheme":"#张继科夸马琳不是人是神#","num":126963,"rank":47,"category":"体育","description":"张继科夸马琳不是人，是神！"},{"word":"梁王组合展望苏迪曼杯","word_scheme":"#梁王组合展望苏迪曼杯#","num":120324,"icon_desc":"新","rank":48,"category":"体育","description":""},{"word":"提前看到了折腰剧宣的混乱场景","word_scheme":"提前看到了折腰剧宣的混乱场景","num":115904,"flag_desc":"剧集","rank":49,"category":"","description":""}]