[{"word":"老人纳凉的成本不能转嫁给肯德基","word_scheme":"#老人纳凉的成本不能转嫁给肯德基#","num":1843081,"icon_desc":"热","rank":0,"category":"社会","description":""},{"word":"程潇向妈妈坦白生病真相","word_scheme":"程潇向妈妈坦白生病真相","num":974086,"icon_desc":"热","flag_desc":"综艺","rank":1,"category":"","description":""},{"word":"第一次从这个视角看高铁洗澡","word_scheme":"#第一次从这个视角看高铁洗澡#","num":949426,"icon_desc":"新","rank":2,"category":"社会","description":""},{"word":"母亲嫌女儿未婚产子丢人将婴儿遗弃","word_scheme":"#母亲嫌女儿未婚产子丢人将婴儿遗弃#","num":941268,"icon_desc":"新","rank":3,"category":"社会","description":"女主播生下失联前男友的儿子，其母亲嫌未婚产子“传出去磕碜”，与2名亲戚合谋将新生儿遗弃在树丛。"},{"word":"山姆给中产丢脸了","word_scheme":"#山姆给中产丢脸了#","num":821254,"icon_desc":"新","rank":4,"category":"财经-产业公司","description":""},{"word":"敖瑞鹏参加过22年重庆山火救援","word_scheme":"敖瑞鹏参加过22年重庆山火救援","num":790120,"icon_desc":"新","rank":5,"category":"","description":""},{"word":"中华小当家男主被处决","word_scheme":"中华小当家男主被处决","num":747645,"icon_desc":"热","rank":6,"category":"","description":""},{"word":"赵露思ELLE首封","word_scheme":"#赵露思ELLE首封#","num":647509,"icon_desc":"热","rank":7,"category":"时尚","description":"这是赵露思第一次拍摄《世界时装之苑ELLE》的封面，却是她与ELLE的老友重逢。"},{"word":"严浩翔养猫","word_scheme":"严浩翔养猫","num":606900,"icon_desc":"新","rank":8,"category":"明星","description":"严浩翔晒新成员，养了两只可爱小猫～🐱"},{"word":"网红靠骂游戏诱导家长买高价课","word_scheme":"#网红靠骂游戏诱导家长买高价课#","num":600497,"icon_desc":"新","rank":9,"category":"社会","description":"网红靠骂游戏诱导家长买高价课，直言游戏“毁了一代孩子”，借此推荐收费的家庭辅导课或戒网瘾训练营"},{"word":"崔始源 我以后会常用微博","word_scheme":"崔始源 我以后会常用微博","num":599417,"icon_desc":"新","rank":10,"category":"","description":""},{"word":"一看就是刘亦菲拍的","word_scheme":"一看就是刘亦菲拍的","num":497172,"icon_desc":"新","rank":11,"category":"","description":""},{"word":"王源鸟巢","word_scheme":"王源鸟巢","num":414854,"icon_desc":"热","flag_desc":"演出","rank":12,"category":"","description":""},{"word":"女子被造黄谣失业抑郁离婚仅获道歉","word_scheme":"#女子被造黄谣失业抑郁离婚仅获道歉#","num":413410,"icon_desc":"新","rank":13,"category":"社会","description":"南宁90后女子被造黄谣后失业、重度抑郁、离婚，维权三年，仅获道歉。"},{"word":"血铅事件27人被追责问责","word_scheme":"#血铅事件27人被追责问责#","num":383542,"rank":14,"category":"社会","description":"7月12日，甘肃省成立省委省政府调查组，提级调查天水市麦积区褐石培心幼儿园幼儿血铅异常问题。"},{"word":"台风韦帕强度将再度发展","word_scheme":"#台风韦帕强度将再度发展#","num":335015,"rank":15,"category":"社会","description":"7月21日，中央气象台继续发布台风黄色预警。"},{"word":"农村大席很少有人吃坏肚子","word_scheme":"农村大席很少有人吃坏肚子","num":303359,"rank":16,"category":"","description":""},{"word":"一个人与一群人吃火锅的区别","word_scheme":"一个人与一群人吃火锅的区别","num":224106,"icon_desc":"新","rank":17,"category":"情感","description":""},{"word":"凡人修仙传剧版和动漫是同班底","word_scheme":"凡人修仙传剧版和动漫是同班底","num":223957,"icon_desc":"新","flag_desc":"剧集","rank":18,"category":"","description":""},{"word":"日本筹建福岛事故后首座核电站","word_scheme":"#日本筹建福岛事故后首座核电站#","num":223442,"icon_desc":"新","rank":19,"category":"时事","description":"日媒：日本筹建福岛事故后首座核电站，民意分歧"},{"word":"余茵从电子厂打工到演厂长被认可","word_scheme":"余茵从电子厂打工到演厂长被认可","num":222836,"icon_desc":"新","rank":20,"category":"","description":""},{"word":"旺仔小乔演唱会 不露脸","word_scheme":"旺仔小乔演唱会 不露脸","num":222456,"icon_desc":"热","flag_desc":"演出","rank":21,"category":"","description":""},{"word":"心动的信号","word_scheme":"心动的信号","num":221839,"icon_desc":"新","flag_desc":"综艺","rank":22,"category":"综艺","description":"《心动的信号》是一档由腾讯视频出品的恋爱观察真人秀，第七季正在热播中，每周一周二12:00更新！"},{"word":"女生为交社保被负债200万","word_scheme":"#女生为交社保被负债200万#","num":221802,"icon_desc":"热","rank":23,"category":"社会","description":""},{"word":"这下轮到哈妮克孜上恋综了","word_scheme":"这下轮到哈妮克孜上恋综了","num":217928,"icon_desc":"新","flag_desc":"综艺","rank":24,"category":"","description":""},{"word":"欧阳妮妮儿子鼻泪管阻塞","word_scheme":"#欧阳妮妮儿子鼻泪管阻塞#","num":217671,"icon_desc":"新","rank":25,"category":"明星","description":""},{"word":"梓渝神图的诞生","word_scheme":"#梓渝神图的诞生#","num":214039,"flag_desc":"演出","rank":26,"category":"明星","description":"梓渝"},{"word":"甘肃疾控中心严重违反操作规程","word_scheme":"#甘肃疾控中心严重违反操作规程#","num":210483,"rank":27,"category":"社会","description":"调查发现，甘肃省疾控中心检测人员7月2日至3日在检测褐石培心幼儿园幼儿和教职员工共267份血液样本时，将检测样本振荡摇匀后静置时间过长（2小时40分钟），导致出现血浆和血细胞分层，取样时未混匀。"},{"word":"易烊千玺2025演唱会礐嶨","word_scheme":"易烊千玺2025演唱会礐嶨","num":206570,"flag_desc":"演出","rank":28,"category":"明星","description":"山间初响，礐嶨将启。@TFBOYS-易烊千玺2025演唱会「礐嶨」首站——上海，8月2日，敬请期待。"},{"word":"小镇出身去留学能改变命运吗","word_scheme":"#小镇出身去留学能改变命运吗#","num":205925,"icon_desc":"新","rank":29,"category":"社会","description":""},{"word":"田栩宁满屏都是留言","word_scheme":"#田栩宁满屏都是留言#","num":205638,"rank":30,"category":"明星","description":""},{"word":"朱珠晒生日合照","word_scheme":"#朱珠晒生日合照#","num":188510,"rank":31,"category":"明星","description":"7月20日下午，@朱珠ZhuZhu在社交平台晒全家福合照。"},{"word":"县委书记挪用6500万用于私利工程","word_scheme":"#县委书记挪用6500万用于私利工程#","num":186245,"icon_desc":"新","rank":32,"category":"社会","description":""},{"word":"印度两兄弟同娶一新娘","word_scheme":"#印度两兄弟同娶一新娘#","num":180346,"rank":33,"category":"社会","description":"7月20日，印度哈蒂部落的两兄弟在喜马偕尔邦的希莱村与同一名女子结婚，数百人见证了这场婚礼，在过去六年里已经举行了五场类似的婚礼。"},{"word":"王俊凯代言花西子","word_scheme":"#王俊凯代言花西子#","num":172740,"rank":34,"category":"明星","description":""},{"word":"12306回应高铁座椅消毒情况","word_scheme":"#12306回应高铁座椅消毒情况#","num":151176,"icon_desc":"新","rank":35,"category":"社会","description":"除了泡面，高铁座椅卫生也受关心，一次性座椅套因此网上热销。12306客服回应：列车始发站和终点站各消毒一次，座椅套若沾染明显污渍会立即更换，但日常清洗时间不固定。目前列车暂不售卖一次性座椅套，乘客可自行准备。铁路部门表示会考虑相关上架建议。"},{"word":"跑男团一日义工行","word_scheme":"#跑男团一日义工行#","num":146564,"icon_desc":"新","flag_desc":"综艺","rank":36,"category":"社会","description":"近日，@浙江卫视“Z公益”携手#奔跑吧#成员@李晨@郑恺@沙溢@白鹿my@卡布叻_周深@范丞丞Adam0616@宋雨琦_i-dle@时代少年团-张真源一起来到中国澳门，以志愿者身份参与“一日义工”活动，关爱流浪动物，致敬默默付出的城市义工，将善举与爱心传递下去。"},{"word":"印度要跟中国比外卖","word_scheme":"印度要跟中国比外卖","num":142183,"rank":37,"category":"","description":""},{"word":"碰瓷中国游客的日本网红当选议员","word_scheme":"碰瓷中国游客的日本网红当选议员","num":141745,"icon_desc":"新","rank":38,"category":"","description":""},{"word":"余承东曝Pura80预售时间","word_scheme":"#余承东曝Pura80预售时间#","num":141707,"icon_desc":"新","rank":39,"category":"互联网","description":""},{"word":"霍汶希杜华给女儿暑假做局","word_scheme":"霍汶希杜华给女儿暑假做局","num":141705,"icon_desc":"新","rank":40,"category":"","description":""},{"word":"内塔尼亚胡食物中毒","word_scheme":"#内塔尼亚胡食物中毒#","num":140797,"rank":41,"category":"时事","description":"据以色列总理办公室20日消息，总理内塔尼亚胡于夜间突感身体不适，经进一步检查后发现是因曾食用变质食物，而患上肠道炎症。"},{"word":"一个人住和爸妈住的区别","word_scheme":"一个人住和爸妈住的区别","num":135403,"icon_desc":"新","rank":42,"category":"搞笑","description":"一个人住和爸妈住的区别"},{"word":"黄子弘凡声而不凡","word_scheme":"#黄子弘凡声而不凡#","num":132309,"icon_desc":"新","flag_desc":"音乐","rank":43,"category":"音乐","description":""},{"word":"印度宣称掌握输电技术","word_scheme":"印度宣称掌握输电技术","num":131840,"icon_desc":"新","rank":44,"category":"","description":""},{"word":"明媒善娶","word_scheme":"明媒善娶","num":131178,"icon_desc":"新","flag_desc":"剧集","rank":45,"category":"电视剧","description":""},{"word":"姜文拍出了马丽不一样的美","word_scheme":"姜文拍出了马丽不一样的美","num":129457,"icon_desc":"新","rank":46,"category":"","description":""},{"word":"你的朋友圈好久没有提及你的快乐了","word_scheme":"你的朋友圈好久没有提及你的快乐了","num":128125,"rank":47,"category":"","description":""},{"word":"明媒善娶定档预告","word_scheme":"#明媒善娶定档预告#","num":126590,"icon_desc":"新","flag_desc":"剧集","rank":48,"category":"电视剧","description":""},{"word":"我选择梓渝21分钟直拍作为我的解药","word_scheme":"我选择梓渝21分钟直拍作为我的解药","num":123439,"icon_desc":"新","flag_desc":"演出","rank":49,"category":"","description":""}]