[{"word":"蔡澜去世","word_scheme":"#蔡澜去世#","num":8250652,"icon_desc":"爆","rank":0,"category":"社会","description":""},{"word":"洞洞鞋 真菌感染","word_scheme":"洞洞鞋 真菌感染","num":1475885,"icon_desc":"新","rank":1,"category":"","description":""},{"word":"2025高考招生录取新变化新趋势","word_scheme":"#2025高考招生录取新变化新趋势#","num":1085482,"icon_desc":"新","rank":2,"category":"社会","description":""},{"word":"鹿晗消瘦模样大变","word_scheme":"#鹿晗消瘦模样大变#","num":1068854,"icon_desc":"新","rank":3,"category":"明星-内地","description":"6月25日，网友在上海遇到鹿晗，瘦成了“纸片人”‌。对于鹿晗的暴瘦，粉丝们也纷纷呼吁他注意身体健康，适当增重。"},{"word":"香港四大才子均已逝世","word_scheme":"#香港四大才子均已逝世#","num":875094,"icon_desc":"新","rank":4,"category":"社会","description":""},{"word":"举报前公婆近亿资产涉贪已有调查结果","word_scheme":"#举报前公婆近亿资产涉贪已有调查结果#","num":460942,"rank":5,"category":"社会","description":"针对女子举报前公婆涉贪一年未有调查结果，南充市发改委表示，因涉及个人隐私因而未将具体核查结果对外公布。"},{"word":"首都民营经济政策宣讲服务团","num":457454,"icon_desc":"荐","rank":5,"category":"时事","description":""},{"word":"金靖私下和周雨彤道歉","word_scheme":"#金靖私下和周雨彤道歉#","num":451513,"icon_desc":"新","rank":6,"category":"明星-内地","description":"🥹🥹🥹🥹"},{"word":"鱿鱼游戏3开播","word_scheme":"鱿鱼游戏3开播","num":449663,"icon_desc":"新","flag_desc":"剧集","rank":7,"category":"电视剧-韩剧","description":""},{"word":"免去苗华中央军事委员会委员职务","word_scheme":"#免去苗华中央军事委员会委员职务#","num":425781,"icon_desc":"新","rank":8,"category":"社会","description":"十四届全国人大常委会第十六次会议27日上午在北京人民大会堂闭幕。会议经表决，免去苗华的中央军事委员会委员职务。"},{"word":"严惩违法出售饲养烈性犬行为","word_scheme":"#严惩违法出售饲养烈性犬行为#","num":390783,"icon_desc":"新","rank":9,"category":"社会","description":"如今依据新规定，违反有关法律法规出售、饲养烈性犬等危险动物，将先处警告；警告后仍不改正，或者致使动物伤害他人的，处五日以下拘留或者一千元以下罚款；情节较重的，处五日以上十日以下拘留。"},{"word":"白玉兰预测","word_scheme":"白玉兰预测","num":389788,"icon_desc":"新","flag_desc":"盛典","rank":10,"category":"电视剧-国产剧","description":""},{"word":"花少7","word_scheme":"花少7","num":382496,"icon_desc":"新","flag_desc":"综艺","rank":11,"category":"","description":""},{"word":"锦绣芳华定档","word_scheme":"锦绣芳华定档","num":358940,"icon_desc":"新","flag_desc":"剧集","rank":12,"category":"电视剧-国产剧","description":""},{"word":"蔡澜的离别信","word_scheme":"#蔡澜的离别信#","num":312024,"icon_desc":"新","rank":13,"category":"社会","description":"6月25日，蔡澜先生离世。27日下午@蔡澜点心发文，公布一封蔡澜先生的信。"},{"word":"机场回应旅客自弃的充电宝如何处置","word_scheme":"#机场回应旅客自弃的充电宝如何处置#","num":249128,"icon_desc":"新","rank":14,"category":"社会","description":"旅客自弃的充电宝机场如何处置？数个机场回应"},{"word":"充电宝 退不了","word_scheme":"充电宝 退不了","num":238387,"rank":15,"category":"","description":""},{"word":"人民网评大学生走廊打地铺避暑","word_scheme":"#人民网评大学生走廊打地铺避暑#","num":207580,"rank":16,"category":"校园","description":""},{"word":"中学生 早恋","word_scheme":"中学生 早恋","num":197717,"rank":17,"category":"","description":""},{"word":"解限机成steam国产游戏榜一大哥","word_scheme":"#解限机成steam国产游戏榜一大哥#","num":197547,"icon_desc":"新","rank":18,"category":"科技","description":""},{"word":"在河南遇见宋画里的山河人间","word_scheme":"#在河南遇见宋画里的山河人间#","num":197387,"icon_desc":"新","rank":19,"category":"社会","description":"2025河南省文化旅游发展大会在八朝古都开封举行，以“文旅焕新消费提质”为主题，带您穿越宋画山河，解锁沉浸式宋韵体验，见证河南文旅新魅力！"},{"word":"蔡澜的微博神回复","word_scheme":"#蔡澜的微博神回复#","num":197228,"icon_desc":"新","rank":20,"category":"社会","description":""},{"word":"男子强奸女儿致其产女又性侵外孙女","word_scheme":"#男子强奸女儿致其产女又性侵外孙女#","num":196920,"icon_desc":"热","rank":21,"category":"社会","description":""},{"word":"上海女硕士被大专男骗财骗色骗卵","word_scheme":"#上海女硕士被大专男骗财骗色骗卵#","num":196800,"rank":22,"category":"社会","description":""},{"word":"田栩宁壁纸","word_scheme":"#田栩宁壁纸#","num":196564,"icon_desc":"新","rank":23,"category":"","description":""},{"word":"李沁花少路透","word_scheme":"李沁花少路透","num":196298,"icon_desc":"新","flag_desc":"综艺","rank":24,"category":"","description":""},{"word":"蔡澜遗体已火化","word_scheme":"#蔡澜遗体已火化#","num":196122,"icon_desc":"新","rank":25,"category":"明星","description":""},{"word":"鹿晗演唱会五哈团建","word_scheme":"#鹿晗演唱会五哈团建#","num":195920,"icon_desc":"新","flag_desc":"演出","rank":26,"category":"综艺","description":""},{"word":"Dior新季期待值拉满","word_scheme":"#Dior新季期待值拉满#","num":195752,"icon_desc":"新","rank":27,"category":"时尚","description":""},{"word":"女子为养胃天天喝烫水查出食管癌","word_scheme":"#女子为养胃天天喝烫水查出食管癌#","num":195434,"rank":28,"category":"社会","description":"郑阿姨觉得吃热的养胃，平时喝水要烫牙，吃饭要烧嘴，已经坚持了二三十年，近期体检发现食管上有可疑病灶，复查确诊了早期食管癌。"},{"word":"杨紫6部待播电视剧电影","word_scheme":"#杨紫6部待播电视剧电影#","num":195361,"icon_desc":"新","rank":29,"category":"明星-内地","description":"6月27日，第30届上海电视节白玉兰奖颁奖典礼将举行，演员@杨紫凭借《国色芳华》再度提名最佳女主角。"},{"word":"郑乃馨发文回应争议","word_scheme":"#郑乃馨发文回应争议#","num":191300,"rank":30,"category":"明星-其他","description":""},{"word":"花少7开始录制","word_scheme":"#花少7开始录制#","num":187247,"icon_desc":"新","flag_desc":"综艺","rank":31,"category":"综艺","description":""},{"word":"古人在90度垂直崖壁上盖了5层楼","word_scheme":"#古人在90度垂直崖壁上盖了5层楼#","num":178688,"icon_desc":"新","rank":32,"category":"社会","description":"山西代县的赵杲观洞窟崖壁建筑群，以天然洞窟为基础修建，距今近1600年。"},{"word":"上海白玉兰颁奖典礼红毯嘉宾阵容","word_scheme":"#上海白玉兰颁奖典礼红毯嘉宾阵容#","num":178373,"icon_desc":"新","flag_desc":"盛典","rank":33,"category":"社会","description":""},{"word":"关晓彤第八套ES顶级高定","word_scheme":"关晓彤第八套ES顶级高定","num":177456,"icon_desc":"新","rank":34,"category":"时尚","description":"关晓彤白玉兰收获第八套ES高定😎"},{"word":"孟子义这段妲己来了都避让三分","word_scheme":"孟子义这段妲己来了都避让三分","num":175229,"icon_desc":"新","rank":35,"category":"","description":""},{"word":"杨紫李现锦绣芳华首发预告","word_scheme":"#杨紫李现锦绣芳华首发预告#","num":171685,"icon_desc":"新","flag_desc":"剧集","rank":36,"category":"社会","description":"牡丹绘锦绣，芳华谱新篇！心怀天下的何惟芳@杨紫蒋长扬@李现ing从渡己助人到救济万民，携手共赴天下万民安居乐业的锦绣盛唐！"},{"word":"天工大纺织专业有多厉害","word_scheme":"天工大纺织专业有多厉害","num":154826,"icon_desc":"新","rank":37,"category":"","description":""},{"word":"蔡澜点心","word_scheme":"蔡澜点心","num":143869,"icon_desc":"新","rank":38,"category":"美食","description":""},{"word":"华为入选全球100大最具影响力企业","word_scheme":"#华为入选全球100大最具影响力企业#","num":139730,"icon_desc":"新","rank":39,"category":"社会","description":"6月26日，美国《时代周刊》公布了2025年“全球100大最具影响力企业”，华为再登时代杂志全球100大企业。"},{"word":"晚晚助理命很苦的感觉","word_scheme":"晚晚助理命很苦的感觉","num":139059,"rank":40,"category":"","description":""},{"word":"只有三天保鲜期的职场KPI","word_scheme":"#只有三天保鲜期的职场KPI#","num":138773,"icon_desc":"新","rank":41,"category":"电视剧","description":""},{"word":"锦绣芳华","word_scheme":"锦绣芳华","num":138758,"rank":42,"category":"电视剧","description":""},{"word":"蔡澜曾谈无儿无女","word_scheme":"#蔡澜曾谈无儿无女#","num":130201,"icon_desc":"新","rank":43,"category":"社会","description":""},{"word":"关晓彤玉兰盛放","word_scheme":"#关晓彤玉兰盛放#","num":119632,"icon_desc":"新","rank":44,"category":"明星","description":"关晓彤玉兰盛放"},{"word":"杭州602分上职业本科女生说不后悔","word_scheme":"#杭州602分上职业本科女生说不后悔#","num":109785,"icon_desc":"新","rank":45,"category":"社会","description":"去年杭州女生高考602分报考职业技术大学，她现状如何？她回应：“挑战自我，大学生活很充实！”"},{"word":"和不熟的人吃饭是加班","word_scheme":"和不熟的人吃饭是加班","num":108114,"icon_desc":"新","rank":46,"category":"","description":""},{"word":"一公园被举报采购天价树每棵近80万","word_scheme":"#一公园被举报采购天价树每棵近80万#","num":107543,"rank":47,"category":"社会","description":"日前，福州市民江先生举报，福州仓山区烟台山公园在景区改造工程中种了多棵“天价树”，一棵黑松采购价发票金额达77.6万元，实际供货价才3.8万元。"},{"word":"体检出现这些指标要当心癌变了","word_scheme":"#体检出现这些指标要当心癌变了#","num":102722,"rank":48,"category":"社会","description":""},{"word":"A股缩量421亿元","word_scheme":"#A股缩量421亿元#","num":101502,"icon_desc":"新","rank":49,"category":"社会","description":"A股缩量421亿元。"}]