[{"word":"青岛大学去世宿管曾收养多只流浪猫","word_scheme":"#青岛大学去世宿管曾收养多只流浪猫#","num":1184551,"icon_desc":"新","rank":0,"category":"社会","description":""},{"word":"常州进球无效","word_scheme":"#常州进球无效#","num":537216,"rank":1,"category":"体育","description":"苏超第六轮，淮安VS常州，常州队第86分钟进球被判无效。优酷体育免费直播2025苏超联赛，看苏超上优酷！"},{"word":"文化中国行看古人的清凉好物","word_scheme":"#文化中国行看古人的清凉好物#","num":526038,"rank":2,"category":"社会","description":""},{"word":"Angelababy出席巴黎时装周","word_scheme":"#Angelababy出席巴黎时装周#","num":522406,"rank":3,"category":"明星","description":"Angelababy参加巴黎高定周，期待美鼻​​​"},{"word":"医生称晚安牛奶每天喝24000瓶才有效","word_scheme":"#医生称晚安牛奶每天喝24000瓶才有效#","num":354518,"rank":4,"category":"社会","description":""},{"word":"学生称去世宿管大爷平时身体很好","word_scheme":"#学生称去世宿管大爷平时身体很好#","num":353995,"icon_desc":"新","rank":5,"category":"社会","description":""},{"word":"CELINE26春季时装秀","num":348941,"icon_desc":"预约","rank":5,"category":"时尚","description":"CELINE2026春季时装秀将于巴黎举行，北京时间7月6日晚8点30分开启线上同步直播，诚邀您共同观赏。"},{"word":"白鹿回应张鑫","word_scheme":"#白鹿回应张鑫#","num":342763,"rank":6,"category":"明星","description":"白鹿回应张鑫"},{"word":"男子借住朋友家一觉醒来6万没了","word_scheme":"#男子借住朋友家一觉醒来6万没了#","num":336161,"icon_desc":"新","rank":7,"category":"社会","description":"湖南永州的周先生反映，自己从和好朋友认识十几年，刚工作回来借住朋友家，但一觉醒来手机里的钱没了。"},{"word":"勿忘19370707","word_scheme":"#勿忘19370707#","num":332529,"rank":8,"category":"社会","description":""},{"word":"石凯晒拍立得","word_scheme":"石凯晒拍立得","num":323130,"icon_desc":"新","rank":9,"category":"","description":""},{"word":"七七事变纪录片一夜之间","word_scheme":"#七七事变纪录片一夜之间#","num":297207,"rank":10,"category":"社会","description":""},{"word":"藏海传床戏","word_scheme":"#藏海传床戏#","num":296070,"icon_desc":"新","rank":11,"category":"电视剧","description":"藏海传床戏"},{"word":"碾压幼童身亡司机称处于视线盲区","word_scheme":"#碾压幼童身亡司机称处于视线盲区#","num":291590,"rank":12,"category":"社会","description":""},{"word":"中考720分小伙高二转职高学烹饪","word_scheme":"#中考720分小伙高二转职高学烹饪#","num":282526,"icon_desc":"新","rank":13,"category":"社会","description":"近日，#自贡18岁小伙获四川烹饪专业第一#。"},{"word":"身份证照片 戴眼镜","word_scheme":"身份证照片 戴眼镜","num":279165,"icon_desc":"热","rank":14,"category":"","description":""},{"word":"血铅异常幼儿异地血检数据升十多倍","word_scheme":"#血铅异常幼儿异地血检数据升十多倍#","num":277708,"icon_desc":"新","rank":15,"category":"社会","description":""},{"word":"BLACKPINK演唱会偶遇邓超孙俪一家","word_scheme":"#BLACKPINK演唱会偶遇邓超孙俪一家#","num":272339,"icon_desc":"新","flag_desc":"演出","rank":16,"category":"明星","description":"blackpink演唱会偶遇邓超孙俪一家"},{"word":"张鑫 白鹿站姐","word_scheme":"张鑫 白鹿站姐","num":267686,"rank":17,"category":"","description":""},{"word":"鹿晗演唱会","word_scheme":"鹿晗演唱会","num":260641,"flag_desc":"演出","rank":18,"category":"音乐-华语音乐","description":""},{"word":"日本呼吁民众做好长期防震准备","word_scheme":"#日本呼吁民众做好长期防震准备#","num":258259,"icon_desc":"新","rank":19,"category":"社会","description":""},{"word":"警方回应拍身份证照片能否戴眼镜","word_scheme":"#警方回应拍身份证照片能否戴眼镜#","num":254368,"icon_desc":"新","rank":20,"category":"社会","description":"金世佳身份证掉了上热搜，12年前能戴眼镜拍照吗？公安部门回应"},{"word":"断眉attention万人大合唱给我唱爽了","word_scheme":"断眉attention万人大合唱给我唱爽了","num":245109,"icon_desc":"新","flag_desc":"演出","rank":21,"category":"","description":""},{"word":"当你的子宫都开始对你催生","word_scheme":"当你的子宫都开始对你催生","num":243133,"icon_desc":"热","flag_desc":"剧集","rank":22,"category":"","description":""},{"word":"王俊凯竟然爱吃折耳根","word_scheme":"王俊凯竟然爱吃折耳根","num":194322,"icon_desc":"新","rank":23,"category":"明星","description":""},{"word":"淮安成首支没赢常州的球队","word_scheme":"#淮安成首支没赢常州的球队#","num":182759,"icon_desc":"新","rank":24,"category":"体育","description":"7月6日晚，苏超第6轮淮安vs常州，双方战成0：0，常州队拿到苏超第1分，淮安成首支没有赢常州的球队。网友：#常州队有分了#，川又变成州了！"},{"word":"无畏 菜","word_scheme":"无畏 菜","num":181990,"rank":25,"category":"","description":""},{"word":"刘诗诗李庚希同框合照","word_scheme":"#刘诗诗李庚希同框合照#","num":178109,"icon_desc":"新","rank":26,"category":"明星-内地","description":""},{"word":"淮上 我就喜欢吃这种的","word_scheme":"淮上 我就喜欢吃这种的","num":168476,"rank":27,"category":"","description":""},{"word":"脊柱最喜欢的4个动作","word_scheme":"#脊柱最喜欢的4个动作#","num":162741,"icon_desc":"新","rank":28,"category":"社会","description":""},{"word":"本月起你的工资或将多一笔钱","word_scheme":"#本月起你的工资或将多一笔钱#","num":158272,"rank":29,"category":"社会","description":""},{"word":"王岳伦机场接王诗龄","word_scheme":"#王岳伦机场接王诗龄#","num":150407,"rank":30,"category":"明星","description":""},{"word":"4岁宝宝手术台上把自己麻晕","word_scheme":"#4岁宝宝手术台上把自己麻晕#","num":145249,"rank":31,"category":"社会","description":""},{"word":"七七事变","word_scheme":"七七事变","num":139803,"icon_desc":"新","rank":32,"category":"政务","description":""},{"word":"李耕耘直播","word_scheme":"李耕耘直播","num":137340,"icon_desc":"新","rank":33,"category":"","description":""},{"word":"这跟Jennie在我脸上跳舞有什么区别","word_scheme":"这跟Jennie在我脸上跳舞有什么区别","num":135274,"icon_desc":"新","flag_desc":"演出","rank":34,"category":"明星-内地","description":""},{"word":"鹿晗今天出场造型","word_scheme":"#鹿晗今天出场造型#","num":133807,"icon_desc":"新","flag_desc":"演出","rank":35,"category":"明星-内地","description":""},{"word":"Bin赛后致歉","word_scheme":"#Bin赛后致歉#","num":128962,"icon_desc":"新","rank":36,"category":"游戏","description":"BLG在今天的MSI正赛0:3不敌T1，Bin在赛后接受LCP媒体的采访:首先很对不起支持我们的粉丝，因为今天这场输得有点难看，希望之后我们会打回来，大家要好好休息！"},{"word":"吃冷饮在嘴里含三五秒真的有用","word_scheme":"#吃冷饮在嘴里含三五秒真的有用#","num":125428,"icon_desc":"新","rank":37,"category":"社会","description":""},{"word":"律师称幼童躺街上被碾司机不会免责","word_scheme":"#律师称幼童躺街上被碾司机不会免责#","num":125256,"icon_desc":"新","rank":38,"category":"社会","description":""},{"word":"日本气象厅再发预警","word_scheme":"#日本气象厅再发预警#","num":124325,"icon_desc":"新","rank":39,"category":"社会","description":"日本气象厅发布预警，提醒民众防范发生震度6弱地震的可能性，并提醒当地民众注意降雨情况。气象厅警告，震感强烈地区存在房屋倒塌和地质灾害风险。"},{"word":"黄子弘凡扶电梯摔倒女生","word_scheme":"#黄子弘凡扶电梯摔倒女生#","num":120740,"rank":40,"category":"明星-内地","description":""},{"word":"男子被钓鱼者甩钩钩住太阳穴","word_scheme":"#男子被钓鱼者甩钩钩住太阳穴#","num":118586,"icon_desc":"新","rank":41,"category":"社会","description":"浙江宁波，一男子太阳穴被一枚带有三根倒刺的鱼钩死死“咬”住，其中两个钩尖分别刺入皮肉，强行拔出极易造成二次伤害。消防员只能先从钩柄薄弱处拆解↓↓"},{"word":"柳智敏澄清ins争议","word_scheme":"#柳智敏澄清ins争议#","num":115974,"rank":42,"category":"明星-日韩","description":"柳智敏澄清ins争议"},{"word":"陈梦妈妈嗑上女儿的糖了","word_scheme":"陈梦妈妈嗑上女儿的糖了","num":112488,"rank":43,"category":"","description":""},{"word":"43岁女子姐弟恋怀孕后婆婆不认可","word_scheme":"#43岁女子姐弟恋怀孕后婆婆不认可#","num":109608,"rank":44,"category":"社会","description":"近日，43岁李女士和二婚男友有了爱情的结晶，但婆婆前后两副面孔让她难以接受，一方面姐弟恋本就压力很大，另一方面婆婆竟质疑腹中孩子，以后该如何面对？"},{"word":"恋与深空严正声明","word_scheme":"恋与深空严正声明","num":107697,"rank":45,"category":"游戏","description":""},{"word":"张雨绮一出场哇声一片","word_scheme":"张雨绮一出场哇声一片","num":105980,"icon_desc":"新","rank":46,"category":"","description":""},{"word":"去看BLACKPINK高阳演唱会的明星","word_scheme":"#去看BLACKPINK高阳演唱会的明星#","num":99150,"flag_desc":"演出","rank":47,"category":"明星","description":"去看BLACKPINK高阳演唱会的明星！"},{"word":"常州1分","word_scheme":"#常州1分#","num":98285,"rank":48,"category":"体育","description":""},{"word":"恋与深空回应剧情去中化","word_scheme":"#恋与深空回应剧情去中化#","num":95688,"rank":49,"category":"游戏","description":""}]