[{"word":"少林寺住持释永信被查","word_scheme":"#少林寺住持释永信被查#","num":1378532,"icon_desc":"沸","rank":0,"category":"社会","description":"少林寺住持释永信涉嫌刑事犯罪，挪用侵占项目资金寺院资产；严重违反佛教戒律，长期与多名女性保持不正当关系并育有私生子。目前正在接受多部门联合调查。有关情况将及时向社会公布"},{"word":"释永信与多名女性保持不正当关系","word_scheme":"#释永信与多名女性保持不正当关系#","num":1058729,"icon_desc":"沸","rank":1,"category":"社会","description":"少林寺住持释永信涉嫌刑事犯罪，挪用侵占项目资金寺院资产；严重违反佛教戒律，长期与多名女性保持不正当关系并育有私生子。目前正在接受多部门联合调查。有关情况将及时向社会公布"},{"word":"数智新时代电商新价值","word_scheme":"#数智新时代电商新价值#","num":752275,"rank":2,"category":"社会","description":""},{"word":"世界肝炎日","num":751965,"icon_desc":"荐","rank":2,"category":"社会","description":"2025年7月28日是第15个\"世界肝炎日\"，我国今年的宣传主题是“社会共治消除肝炎”。"},{"word":"释永信已全面主持少林寺38年","word_scheme":"#释永信已全面主持少林寺38年#","num":748392,"icon_desc":"热","rank":3,"category":"时事","description":"释永信是在2025年7月25日前后，被河南新乡警方带走的。此前，释永信已经全面主持少林寺的寺院事务工作长达38年。"},{"word":"汪苏泷这一跪又有多少人沦陷了","word_scheme":"汪苏泷这一跪又有多少人沦陷了","num":725280,"icon_desc":"热","flag_desc":"演出","rank":4,"category":"音乐","description":"汪苏泷这一跪又有多少人沦陷"},{"word":"国外司机与13岁巴士迷车内发生关系","word_scheme":"#国外司机与13岁巴士迷车内发生关系#","num":541259,"rank":5,"category":"社会","description":"与13岁“巴士迷”在车内发生性关系，新加坡一巴士司机被判八年"},{"word":"释永信育有私生子","word_scheme":"#释永信育有私生子#","num":404782,"rank":6,"category":"社会","description":""},{"word":"李兰迪扫腿舞地是干净了","word_scheme":"#李兰迪扫腿舞地是干净了#","num":384641,"rank":7,"category":"明星","description":"李兰迪跳扫腿舞地是干净了"},{"word":"释永信涉嫌刑事犯罪","word_scheme":"#释永信涉嫌刑事犯罪#","num":381934,"rank":8,"category":"社会","description":""},{"word":"山西失联客车找到1名遇难者","word_scheme":"#山西失联客车找到1名遇难者#","num":371222,"icon_desc":"新","rank":9,"category":"社会","description":"山西天镇县一车辆遇险失联，已搜寻到一名遇难者。"},{"word":"释永信老婆","word_scheme":"#释永信老婆#","num":371089,"icon_desc":"热","rank":10,"category":"","description":""},{"word":"释延鲁","word_scheme":"释延鲁","num":370886,"icon_desc":"热","rank":11,"category":"","description":""},{"word":"为什么很少听说数学系的学生被压榨","word_scheme":"为什么很少听说数学系的学生被压榨","num":370529,"rank":12,"category":"","description":""},{"word":"美国与欧盟达成贸易协议","word_scheme":"#美国与欧盟达成贸易协议#","num":344640,"rank":13,"category":"时事","description":"当地时间7月27日，美国总统特朗普表示，美国已与欧盟达成贸易协议，对欧盟输美商品征收15%的关税。"},{"word":"生理期真正不能做的10件事","word_scheme":"#生理期真正不能做的10件事#","num":252920,"rank":14,"category":"科普","description":"月经期间，女性应该少做这10件事，以免对身体造成伤害。"},{"word":"张子萱脑供氧不足","word_scheme":"张子萱脑供氧不足","num":248011,"icon_desc":"新","rank":15,"category":"明星","description":""},{"word":"多支增援力量已抵达北京受灾一线","word_scheme":"#多支增援力量已抵达北京受灾一线#","num":231661,"rank":16,"category":"社会","description":"昨夜今晨强降雨影响，北京密云区白马关河洪水暴涨，部分道路损坏，村庄电力网络中断，武警北京总队执勤第八支队携带冲锋舟以及抢险物资在冯家峪镇投入抢险救援工作。目前，先期投入的部队正在全力展开救援，多支增援力量已抵达受灾一线，有序展开抢险救援工作。"},{"word":"南京照相馆票房","word_scheme":"南京照相馆票房","num":227159,"icon_desc":"新","rank":17,"category":"","description":""},{"word":"深情眼你敢演我不敢看了","word_scheme":"深情眼你敢演我不敢看了","num":222760,"icon_desc":"新","flag_desc":"剧集","rank":18,"category":"","description":""},{"word":"沈佳润写了美美桑内中文版歌词","word_scheme":"沈佳润写了美美桑内中文版歌词","num":220758,"flag_desc":"音乐","rank":19,"category":"","description":""},{"word":"女子生气抓男友头发撞墙致其去世","word_scheme":"#女子生气抓男友头发撞墙致其去世#","num":220743,"rank":20,"category":"社会","description":"女子分手遭男友自残式挽留，抓男友头发撞墙致其去世，法院：故意伤害罪获刑11年"},{"word":"越吃越胖的素菜名单","word_scheme":"#越吃越胖的素菜名单#","num":220221,"icon_desc":"新","rank":21,"category":"科普","description":"素菜里有不少“吸油大户”，不恰当的做法可导致其脂肪含量增加数百倍，尤其是以下几类。"},{"word":"少林寺官号已删除多篇涉释永信文章","word_scheme":"#少林寺官号已删除多篇涉释永信文章#","num":199142,"icon_desc":"新","rank":22,"category":"财经","description":""},{"word":"女孩患胃萎缩从90多斤暴瘦至35斤","word_scheme":"#女孩患胃萎缩从90多斤暴瘦至35斤#","num":198320,"icon_desc":"新","rank":23,"category":"社会","description":"7月27日报道，27岁女孩患胃萎缩发视频求助，体重从90多斤暴瘦至35斤！从小被妈妈抛弃，爸爸患胃癌晚期去世，如今只剩弟弟和自己相依为命，为治病花光所有积蓄，只能靠吃药打白蛋白营养液维持希望。"},{"word":"释永信涉嫌挪用侵占寺院资产","word_scheme":"#释永信涉嫌挪用侵占寺院资产#","num":193333,"rank":24,"category":"社会","description":""},{"word":"国家安全部披露间谍常用套路","word_scheme":"#国家安全部披露间谍常用套路#","num":183836,"icon_desc":"新","rank":25,"category":"社会","description":"国家安全部结合多起案例特点，揭露间谍常用“套路”↓↓"},{"word":"少林景区将全面实行线上预约购票","word_scheme":"#少林景区将全面实行线上预约购票#","num":174703,"rank":26,"category":"社会","description":""},{"word":"宁宁","word_scheme":"宁宁","num":169720,"flag_desc":"演出","rank":27,"category":"","description":""},{"word":"鹿晗扫腿舞星奇摇","word_scheme":"#鹿晗扫腿舞星奇摇#","num":169253,"flag_desc":"演出","rank":28,"category":"明星","description":"鹿晗演唱会跳了扫腿舞和星奇摇！"},{"word":"鹿晗金宣虎笑","word_scheme":"#鹿晗金宣虎笑#","num":169222,"flag_desc":"演出","rank":29,"category":"明星","description":""},{"word":"张本美和女单冠军","word_scheme":"#张本美和女单冠军#","num":169221,"icon_desc":"新","rank":30,"category":"体育","description":""},{"word":"带着轻微饥饿感入睡能瘦吗","word_scheme":"#带着轻微饥饿感入睡能瘦吗#","num":152771,"rank":31,"category":"社会","description":"近日，医生讲解饥饿感对减肥的作用：保持轻微饥饿感入睡是变瘦的开始。"},{"word":"首席预报员分析北京本轮雨情","word_scheme":"#首席预报员分析北京本轮雨情#","num":147751,"icon_desc":"新","rank":32,"category":"社会","description":"昨晚，在副高边缘西南暖湿气流的影响下，北京市北部地区出现了非常强的短时强降水天气。"},{"word":"前央视主持人杨茗茗离职后自曝后悔","word_scheme":"#前央视主持人杨茗茗离职后自曝后悔#","num":137184,"icon_desc":"新","rank":33,"category":"社会","description":"2021年，前央视体育频道主持人杨茗茗官宣离开央视。7月24号，杨茗茗首度分享了离职四年以来的心酸过往，表示自己后悔了。但她后悔的并非是离开央视，而是离职前没有做好详细的市场需求规划，对商业险恶认知不足，也没料到人心如此凉薄。"},{"word":"印度女子昏迷在救护车遭轮奸","word_scheme":"#印度女子昏迷在救护车遭轮奸#","num":135789,"rank":34,"category":"社会","description":"7月27日，据印度媒体报道，一名26岁女子在比哈尔邦加雅区参加国民警卫队招募活动时，体能测试时晕倒，在被送往医院的一辆行驶中的救护车上遭到轮奸。"},{"word":"央视曝光私域直播坑老骗局","word_scheme":"#央视曝光私域直播坑老骗局#","num":132727,"rank":35,"category":"财经","description":"#总台财经调查#接到消费者反映，市场上有人打着“银发经济”的幌子，专做坑老骗老的勾当。"},{"word":"韩国热到冰美式都不冰了","word_scheme":"#韩国热到冰美式都不冰了#","num":131256,"rank":36,"category":"财经","description":"在首尔地区，因清凉口感和提神效果备受当地居民欢迎的冰美式咖啡，在居高不下的气温中，都变得“不冰了”。"},{"word":"王楚钦奥沙利文互赠to签礼物","word_scheme":"#王楚钦奥沙利文互赠to签礼物#","num":129551,"icon_desc":"新","rank":37,"category":"体育","description":""},{"word":"杭州开市客门店已下架麻六记酸辣粉","word_scheme":"#杭州开市客门店已下架麻六记酸辣粉#","num":127304,"icon_desc":"新","rank":38,"category":"社会","description":"橙柿互动记者以消费者身份致电开市客杭州门店，门店客服回应麻六记酸辣粉确已全部下架，如果此前有购买该款商品需要退的，可以带着商品到开市客进行退款。"},{"word":"天下无神皆是凡人","word_scheme":"天下无神皆是凡人","num":121000,"icon_desc":"新","rank":39,"category":"","description":""},{"word":"居然之家","word_scheme":"居然之家","num":120298,"rank":40,"category":"其他","description":"居然之家是以“大家居”为主业，以“让家装家居快乐简单”为企业使命，业务范围涵盖室内设计和装修、家具建材销售、智慧物流、金融服务、现代百货、购物中心、超市、院线餐饮、儿童娱乐、体育健身、数码智能、居家养老等领域的大型商业连锁集团公司。"},{"word":"男子约见台球助教收到5000元清单","word_scheme":"#男子约见台球助教收到5000元清单#","num":119723,"rank":41,"category":"社会","description":"浙江杭州，丁先生在网上认识了一名台球助教，两人约到台球厅见面。说是当时来了很多对方的小姐妹，“围了一大圈”，点了不少东西，光啤酒就有55瓶。最后，丁先生收到了一张长长的清单，金额有5000元。丁先生说，因为结账的事，他的头被打肿了。"},{"word":"漫展门口卖笔骗局","word_scheme":"漫展门口卖笔骗局","num":112913,"icon_desc":"新","rank":42,"category":"","description":""},{"word":"原来这就是属于00后的红利","word_scheme":"原来这就是属于00后的红利","num":108294,"icon_desc":"新","rank":43,"category":"","description":""},{"word":"被喜欢的东西叫醒是不会有起床气的","word_scheme":"被喜欢的东西叫醒是不会有起床气的","num":95094,"rank":44,"category":"","description":""},{"word":"10号台风白鹿即将生成或直奔江浙沪","word_scheme":"#10号台风白鹿即将生成或直奔江浙沪#","num":92819,"rank":45,"category":"社会","description":"7月27日，据浙江天气报道，热带低压91W很有可能成为今年的10号台风白鹿，并将直奔江浙沪而来。"},{"word":"李小冉说一路繁花塌的也不是我","word_scheme":"#李小冉说一路繁花塌的也不是我#","num":89248,"rank":46,"category":"明星","description":""},{"word":"人真的会突然变好","word_scheme":"人真的会突然变好","num":88164,"icon_desc":"新","rank":47,"category":"","description":""},{"word":"偶遇李冰冰管乐手挽手看舞剧","word_scheme":"偶遇李冰冰管乐手挽手看舞剧","num":87119,"rank":48,"category":"","description":""},{"word":"欧盟将对美增加6000亿美元投资","word_scheme":"#欧盟将对美增加6000亿美元投资#","num":85759,"rank":49,"category":"时事","description":"美国将对欧盟输美产品征收15%的关税、欧盟将对美增加6000亿美元投资及购买价值7500亿美元的美国能源"}]