[{"word":"没去芭莎的很幸运了","word_scheme":"没去芭莎的很幸运了","num":1701498,"icon_desc":"新","rank":0,"category":"明星","description":"非常考验颜值的芭莎镜头签✨谁抗住了？​​​"},{"word":"株洲母子车祸1死1伤案家属发声","word_scheme":"#株洲母子车祸1死1伤案家属发声#","num":651846,"icon_desc":"新","rank":1,"category":"社会","description":""},{"word":"端午气氛组强势上线","word_scheme":"#端午气氛组强势上线#","num":583894,"icon_desc":"新","rank":2,"category":"社会","description":"随着端午日益临近，在河南鹤壁，传统和创意兼具的粽子、香囊等商品开始在市场上热销，节日氛围愈发浓厚。“五月五，龙船鼓。”广东是中国龙舟文化的重要发源地之一，"},{"word":"天猫618今晚8点开卖","num":583005,"icon_desc":"火热","rank":2,"category":"互联网","description":"5月28日晚8点天猫618狂欢节正式开卖！立减！85折起叠9折无门槛大额消费券，笔笔9折，最高减1000元！更有官方补贴每人最高可领11118元！晚8买更便宜，天猫618补贴真的大立减真低价！"},{"word":"藏海传24集 新的太子","word_scheme":"藏海传24集 新的太子","num":582938,"icon_desc":"新","flag_desc":"剧集","rank":3,"category":"","description":""},{"word":"端午不调休 高速不免费","word_scheme":"端午不调休 高速不免费","num":579745,"icon_desc":"热","rank":4,"category":"","description":""},{"word":"游客发现武陵山天池底为304不锈钢","word_scheme":"#游客发现武陵山天池底为304不锈钢#","num":515119,"rank":5,"category":"社会","description":"近日，有游客在重庆武陵山森林公园发现了“不锈钢天池”。"},{"word":"618飞猪超级VIP暑期不加价","num":511090,"icon_desc":"官宣","rank":5,"category":"旅游","description":"又到周三！飞猪超级VIP618海量爆款上新，超多旅行尖货暑期不加价。直播间等你来抢！"},{"word":"鞠婧祎 蛇女","word_scheme":"鞠婧祎 蛇女","num":508513,"icon_desc":"热","rank":6,"category":"","description":""},{"word":"杨幂躲镜头","word_scheme":"#杨幂躲镜头#","num":498214,"icon_desc":"新","flag_desc":"盛典","rank":7,"category":"明星-内地","description":"杨幂在芭莎红毯镜头签那里躲镜头了，还比了个耶，哈哈哈哈，你真调皮"},{"word":"芭莎内场","word_scheme":"芭莎内场","num":417818,"rank":8,"category":"","description":""},{"word":"总监降职为前台公司被判赔26万","word_scheme":"#总监降职为前台公司被判赔26万#","num":416347,"icon_desc":"新","rank":9,"category":"社会","description":"总监被降职为前台，虽然待遇不变，但这样的调岗合法吗？打官司谁会赢？申工社5月28日的一则普法报道引发热议。"},{"word":"刘宇宁 锡纸抹胸","word_scheme":"刘宇宁 锡纸抹胸","num":410543,"icon_desc":"新","rank":10,"category":"","description":""},{"word":"结婚4天就离男子获退18万彩礼","word_scheme":"#结婚4天就离男子获退18万彩礼#","num":400088,"rank":11,"category":"社会","description":""},{"word":"林允身材好绝","word_scheme":"#林允身材好绝#","num":395364,"icon_desc":"热","rank":12,"category":"明星","description":""},{"word":"于正 吴谨言又杀回来了","word_scheme":"于正 吴谨言又杀回来了","num":386193,"icon_desc":"热","rank":13,"category":"","description":""},{"word":"卫生巾 妇科感染","word_scheme":"卫生巾 妇科感染","num":382895,"rank":14,"category":"","description":""},{"word":"荣耀新CEO李健国内首秀","word_scheme":"#荣耀新CEO李健国内首秀#","num":373009,"icon_desc":"新","rank":15,"category":"数码","description":"在5月28日荣耀400系列发布会上，新任CEO李健以三则真实故事解构品牌内核，勾勒出“真实就是力量”的哲学图景。这种从人文洞察出发的品牌立意，正在重新定义科技企业的温度边界。"},{"word":"荣耀CEO李健发布会首发微博","word_scheme":"#荣耀CEO李健发布会首发微博#","num":366632,"icon_desc":"新","rank":16,"category":"数码","description":""},{"word":"这次是林志玲酷玲","word_scheme":"这次是林志玲酷玲","num":362010,"icon_desc":"新","rank":17,"category":"","description":""},{"word":"销售回应女生装大人疯狂下单化妆品","word_scheme":"#销售回应女生装大人疯狂下单化妆品#","num":354987,"icon_desc":"新","rank":18,"category":"社会","description":""},{"word":"四川一中学校长被曝殴打学生","word_scheme":"#四川一中学校长被曝殴打学生#","num":345693,"icon_desc":"新","rank":19,"category":"社会","description":"5月27日，四川德阳中江县仓山镇初级中学一家长反映，因女儿打扫卫生时声音大遭校长刘某某殴打。家长提供的视频显示：孩子双腿外侧有污渍，捞起裤子后皮肤红肿。"},{"word":"易梦玲的脸","word_scheme":"易梦玲的脸","num":341961,"rank":20,"category":"","description":""},{"word":"妈妈幂呀","word_scheme":"妈妈幂呀","num":304539,"rank":21,"category":"","description":""},{"word":"外交部回应辽宁舰为何如此靠近日本","word_scheme":"#外交部回应辽宁舰为何如此靠近日本#","num":295865,"rank":22,"category":"时事","description":"辽宁舰经过日本南部岛屿是否在向日美及台湾地区发出信号？外交部回应"},{"word":"方时赫或将入狱","word_scheme":"#方时赫或将入狱#","num":274931,"icon_desc":"热","rank":23,"category":"明星-日韩","description":"方时赫或将入狱"},{"word":"荣耀AI意图识别引擎行业领先","word_scheme":"#荣耀AI意图识别引擎行业领先#","num":274829,"icon_desc":"新","rank":24,"category":"数码","description":""},{"word":"吴谨言的家政秘籍藏不住了","word_scheme":"#吴谨言的家政秘籍藏不住了#","num":274741,"icon_desc":"新","rank":25,"category":"明星","description":""},{"word":"男子与被告同名同姓被执行还陌生人钱","word_scheme":"#男子与被告同名同姓被执行还陌生人钱#","num":274666,"icon_desc":"新","rank":26,"category":"社会","description":"男子因与被告同名同姓被执行还陌生人钱。"},{"word":"荣耀400听劝换大电池了","word_scheme":"#荣耀400听劝换大电池了#","num":274530,"icon_desc":"新","rank":27,"category":"社会","description":"调查显示，很多人手机电量低于50%就会焦虑，未来手机电池持续“扩容”已成大势所趋，对此你怎么看？"},{"word":"无效社交真的是浪费时间吗","word_scheme":"无效社交真的是浪费时间吗","num":274465,"icon_desc":"新","rank":28,"category":"","description":""},{"word":"男子在生殖医院做手术次日身亡进展","word_scheme":"#男子在生殖医院做手术次日身亡进展#","num":274367,"icon_desc":"新","rank":29,"category":"社会","description":""},{"word":"大麦崩了","word_scheme":"大麦崩了","num":274301,"icon_desc":"新","flag_desc":"演出","rank":30,"category":"明星","description":""},{"word":"张凌赫内场赢麻了","word_scheme":"张凌赫内场赢麻了","num":251428,"icon_desc":"新","rank":31,"category":"","description":""},{"word":"刘宇宁直播","word_scheme":"刘宇宁直播","num":246246,"rank":32,"category":"明星","description":""},{"word":"在人间热度","word_scheme":"#在人间热度#","num":224077,"flag_desc":"剧集","rank":33,"category":"电视剧","description":"在人间热度"},{"word":"在人间","word_scheme":"在人间","num":193193,"rank":34,"category":"电视剧","description":"《在人间》定档0528在你的世界，寻找你。"},{"word":"aespa小品女王","word_scheme":"aespa小品女王","num":191519,"icon_desc":"新","flag_desc":"音乐","rank":35,"category":"","description":""},{"word":"虞书欣谢可寅你俩喝点中药吧","word_scheme":"虞书欣谢可寅你俩喝点中药吧","num":183603,"icon_desc":"新","flag_desc":"剧集","rank":36,"category":"","description":""},{"word":"越过山丘发现无人等候终于懂了","word_scheme":"越过山丘发现无人等候终于懂了","num":179186,"icon_desc":"新","rank":37,"category":"社会","description":""},{"word":"肖战同款荣耀400发布","word_scheme":"#肖战同款荣耀400发布#","num":177675,"rank":38,"category":"明星","description":""},{"word":"美团澄清称不惜代价是指反内卷","word_scheme":"#美团澄清称不惜代价是指反内卷#","num":176510,"icon_desc":"新","rank":39,"category":"财经","description":""},{"word":"孙俪 摇曳生姿的黑玫瑰","word_scheme":"孙俪 摇曳生姿的黑玫瑰","num":176429,"icon_desc":"新","rank":40,"category":"","description":""},{"word":"U16国足2比1沙特U16","word_scheme":"#U16国足2比1沙特U16#","num":176409,"icon_desc":"新","rank":41,"category":"体育","description":"呼和浩特国际足球锦标赛，U16国足2-1击败沙特U16，取得开门红！帅惟浩91分钟头球绝杀，何思凡挑射破门，邝兆镭献助攻。"},{"word":"洪小铃产后首次露面","word_scheme":"#洪小铃产后首次露面#","num":175425,"icon_desc":"新","rank":42,"category":"社会","description":"日前，47岁演员洪小铃产后首次露面。"},{"word":"赵丽颖下意识演员天赋型选手","word_scheme":"赵丽颖下意识演员天赋型选手","num":168806,"rank":43,"category":"","description":""},{"word":"荣耀400","word_scheme":"#荣耀400#","num":166888,"icon_desc":"新","rank":44,"category":"","description":""},{"word":"医生未做皮试输青霉素致患者死亡获刑","word_scheme":"#医生未做皮试输青霉素致患者死亡获刑#","num":159599,"rank":45,"category":"社会","description":"医师未按规范要求在输注青霉素前对患者进行皮肤试验，后患者因药物过敏性休克致呼吸循环衰竭死亡。"},{"word":"香暗荼你被捕了","word_scheme":"#香暗荼你被捕了#","num":150740,"icon_desc":"新","flag_desc":"剧集","rank":46,"category":"明星","description":""},{"word":"乒超","word_scheme":"乒超","num":150376,"rank":47,"category":"","description":""},{"word":"HLE连续八次击败T1","word_scheme":"#HLE连续八次击败T1#","num":137248,"icon_desc":"新","rank":48,"category":"游戏","description":""},{"word":"韩红的压力已经给到内娱了","word_scheme":"韩红的压力已经给到内娱了","num":128359,"rank":49,"category":"综艺","description":"隔着屏幕都感受到韩红老师的认真与严厉了！建议以后内娱这样卷起来！"}]