[{"word":"水蒸蛋被改名日本蒸蛋","word_scheme":"水蒸蛋被改名日本蒸蛋","num":1145488,"icon_desc":"热","rank":0,"category":"","description":""},{"word":"家里吧唧太多女孩深夜中毒送医","word_scheme":"#家里吧唧太多女孩深夜中毒送医#","num":589239,"rank":1,"category":"社会","description":"家里“吧唧”太多会要命？女孩深夜就医……"},{"word":"今日入伏","word_scheme":"#今日入伏#","num":494309,"rank":2,"category":"社会","description":"三伏天来了"},{"word":"韩国人装中国人在泰国打架","word_scheme":"韩国人装中国人在泰国打架","num":481771,"icon_desc":"热","rank":3,"category":"","description":""},{"word":"杨洋回宫","word_scheme":"杨洋回宫","num":417208,"icon_desc":"新","flag_desc":"剧集","rank":4,"category":"","description":""},{"word":"程潇曾患双相情感障碍","word_scheme":"#程潇曾患双相情感障碍#","num":390334,"icon_desc":"新","flag_desc":"综艺","rank":5,"category":"综艺-内地综艺","description":""},{"word":"网传杭州水务集团刘某某潜逃系谣言","num":370190,"icon_desc":"辟谣","rank":5,"category":"社会","description":""},{"word":"白举纲XXXXXL牛仔裤","word_scheme":"白举纲XXXXXL牛仔裤","num":364508,"icon_desc":"新","flag_desc":"演出","rank":6,"category":"","description":""},{"word":"丁禹兮扫腿舞","word_scheme":"#丁禹兮扫腿舞#","num":362677,"icon_desc":"新","rank":7,"category":"明星","description":""},{"word":"691分考上北大惊动了宗族长老","word_scheme":"691分考上北大惊动了宗族长老","num":335791,"icon_desc":"热","rank":8,"category":"","description":""},{"word":"美IT大佬出轨门女方老公也是CEO","word_scheme":"#美IT大佬出轨门女方老公也是CEO#","num":330793,"icon_desc":"新","rank":9,"category":"社会","description":""},{"word":"演唱会被曝出轨女方与丈夫5月前购豪宅","word_scheme":"#演唱会被曝出轨女方与丈夫5月前购豪宅#","num":322987,"icon_desc":"热","rank":10,"category":"社会","description":""},{"word":"农民工为了12元差点被烤熟","word_scheme":"农民工为了12元差点被烤熟","num":316382,"icon_desc":"新","rank":11,"category":"","description":""},{"word":"上海蝉尿如下雨","word_scheme":"上海蝉尿如下雨","num":310769,"rank":12,"category":"","description":""},{"word":"田栩宁四宫格照","word_scheme":"#田栩宁四宫格照#","num":305148,"rank":13,"category":"明星-内地","description":""},{"word":"佛山两区号召全体市民灭蚊","word_scheme":"#佛山两区号召全体市民灭蚊#","num":302753,"icon_desc":"新","rank":14,"category":"社会","description":""},{"word":"三个少年","word_scheme":"三个少年","num":301663,"icon_desc":"新","flag_desc":"综艺","rank":15,"category":"综艺","description":"《三个少年》第三季敬请期待！"},{"word":"州在今天拥有了常","word_scheme":"州在今天拥有了常","num":292019,"icon_desc":"新","rank":16,"category":"体育","description":""},{"word":"梓渝彩排特写","word_scheme":"#梓渝彩排特写#","num":289604,"icon_desc":"新","flag_desc":"演出","rank":17,"category":"明星","description":"梓渝彩排特写来啦！好有氛围感！"},{"word":"泰警方确认餐厅斗殴者系韩国游客","word_scheme":"#泰警方确认餐厅斗殴者系韩国游客#","num":288637,"icon_desc":"新","rank":18,"category":"社会","description":""},{"word":"一种儿童玩具100度高温220伏电压","word_scheme":"#一种儿童玩具100度高温220伏电压#","num":262336,"icon_desc":"新","rank":19,"category":"社会","description":"一些“网红电器”如迷你爆米花机、棉花糖机等，特意做成类似玩具的造型，标有“儿童节礼物”等字样，吸引儿童购买。然而，玩具的表面温度能达到100℃以上。"},{"word":"欲望羞耻","word_scheme":"欲望羞耻","num":262283,"icon_desc":"新","rank":20,"category":"","description":""},{"word":"三伏天 减肥","word_scheme":"三伏天 减肥","num":256572,"rank":21,"category":"","description":""},{"word":"梓渝音乐节","word_scheme":"梓渝音乐节","num":237983,"flag_desc":"演出","rank":22,"category":"明星-内地","description":""},{"word":"英雄联盟","word_scheme":"英雄联盟","num":207174,"icon_desc":"新","rank":23,"category":"游戏","description":"2025年英雄联盟Uzi名人堂活动6月12日开启，请锁定英雄联盟官方直播间，重磅嘉宾及丰富福利等你来！"},{"word":"陈梦准备恢复训练了","word_scheme":"#陈梦准备恢复训练了#","num":199358,"icon_desc":"新","rank":24,"category":"体育","description":"陈梦谈全运会备战：已经开始要准备恢复训练了，因为确实已经有半年没有训练了，虽然有断断续续的偶尔活动，但是也都是不是正规的训练，所以还是要好好准备一下。"},{"word":"龚俊我真服了3.0版","word_scheme":"龚俊我真服了3.0版","num":199266,"icon_desc":"新","rank":25,"category":"电视剧","description":"《狐妖小红娘月红篇》发布会，龚俊“我真服了”3.0版"},{"word":"敖瑞鹏李兰迪短剧式剧宣","word_scheme":"#敖瑞鹏李兰迪短剧式剧宣#","num":196842,"icon_desc":"新","rank":26,"category":"明星-内地","description":"7月20日，@敖瑞鹏的微博@李兰迪《朝雪录》双人共创短剧式剧宣来了，网友:“好抽象的剧宣！敖瑞鹏、李兰迪成功闯进新赛道！”"},{"word":"农夫山泉官方到处解释","word_scheme":"农夫山泉官方到处解释","num":191586,"rank":27,"category":"","description":""},{"word":"MRC对战DOU5","word_scheme":"#MRC对战DOU5#","num":184808,"icon_desc":"新","rank":28,"category":"游戏","description":"#MRC对战DOU5#IVL秋季赛总决赛第三日打响，半决赛由常规赛第二名的dou5对战第三名的mrc，你觉得谁能晋级决赛呢？"},{"word":"河北小伙回应在加拿大当公务员","word_scheme":"#河北小伙回应在加拿大当公务员#","num":179837,"icon_desc":"新","rank":29,"category":"社会","description":"老家位于河北的小伙Astro上岸了公务员，不同的是，他是在加拿大做公务员。“加拿大公务员的报考流程有点像企业招聘，每个人都可以一次性报很多不同的岗位。”"},{"word":"北大在湖北招生出现空档","word_scheme":"#北大在湖北招生出现空档#","num":179780,"icon_desc":"新","rank":30,"category":"教育","description":""},{"word":"俄罗斯海域6.7级7.4级6.7级地震","word_scheme":"#俄罗斯海域6.7级7.4级6.7级地震#","num":173394,"icon_desc":"新","rank":31,"category":"社会","description":"据美国地质调查局地震信息网消息，俄罗斯远东堪察加半岛附近海域20日接连发生6.7级、7.4级和6.7级地震后，引发海啸预警。"},{"word":"美又解雇70名外国研究员多为中国博后","word_scheme":"#美又解雇70名外国研究员多为中国博后#","num":172153,"icon_desc":"新","rank":32,"category":"时事","description":"外媒：美农业部又以“国家安全”为由解雇70名外国合同制研究员，“多数是中国博士后”"},{"word":"女子称因生女儿公公想过继孙子给自己","word_scheme":"#女子称因生女儿公公想过继孙子给自己#","num":161034,"rank":33,"category":"社会","description":"7月19日(发布)，河南郑州，八旬老人想过继孙子，儿媳现场倒苦水。儿媳：结婚时老公是独生子，过了30年，公公又冒出来其他儿子孙子，“公公还要过继给我一个男孩，我有女儿！”"},{"word":"wakuku","word_scheme":"wakuku","num":148663,"rank":34,"category":"","description":""},{"word":"张凌赫没人喜欢蠢的吧","word_scheme":"张凌赫没人喜欢蠢的吧","num":146766,"rank":35,"category":"电视剧","description":""},{"word":"佛山累计基孔肯雅热确诊1873例","word_scheme":"#佛山累计基孔肯雅热确诊1873例#","num":146340,"icon_desc":"新","rank":36,"category":"社会","description":""},{"word":"吧唧 甲醛","word_scheme":"吧唧 甲醛","num":128303,"icon_desc":"新","rank":37,"category":"","description":""},{"word":"去了twice演唱会的明星","word_scheme":"#去了twice演唱会的明星#","num":123886,"icon_desc":"新","flag_desc":"演出","rank":38,"category":"明星","description":"好多人去了twice演唱会！"},{"word":"张子宇杨瀚森都是山东顶级天赋","word_scheme":"#张子宇杨瀚森都是山东顶级天赋#","num":120826,"icon_desc":"新","rank":39,"category":"体育","description":"网友：一个济南小嫚、一个淄博小伙。未来十年中国篮球两大支柱都在鲁中这一百公里内了！"},{"word":"24岁女生吃串串香2年查出胃癌晚期","word_scheme":"#24岁女生吃串串香2年查出胃癌晚期#","num":118109,"rank":40,"category":"社会","description":"河南郑州一名24岁刚毕业的女大学生，竟被查出胃癌晚期！医生追问病史发现，她在校期间至少两年几乎每天吃校门口地摊串串香，还长期不吃晚饭，胃黏膜长期受损。"},{"word":"樊振东图形商标注册成功","word_scheme":"#樊振东图形商标注册成功#","num":117207,"icon_desc":"新","rank":41,"category":"体育","description":"樊振东图形商标注册成功"},{"word":"单休怎么休最回血","word_scheme":"单休怎么休最回血","num":110235,"icon_desc":"新","rank":42,"category":"","description":""},{"word":"刘亦菲朱珠 小说里玩得好的千金小姐","word_scheme":"刘亦菲朱珠 小说里玩得好的千金小姐","num":110175,"rank":43,"category":"","description":""},{"word":"广东全省转移超27万人","word_scheme":"#广东全省转移超27万人#","num":107434,"icon_desc":"新","rank":44,"category":"社会","description":"为防御今年第6号台风“韦帕”，切实保障群众生命财产安全，广东多地积极做好渔船回港、人员上岸、危险区域群众转移安置等工作。"},{"word":"小沈阳 Nina黑粉","word_scheme":"小沈阳 Nina黑粉","num":102000,"flag_desc":"演出","rank":45,"category":"","description":""},{"word":"罗小黑2有20万张原画","word_scheme":"罗小黑2有20万张原画","num":101623,"icon_desc":"新","flag_desc":"电影","rank":46,"category":"","description":""},{"word":"基孔肯雅热","word_scheme":"基孔肯雅热","num":100263,"icon_desc":"新","rank":47,"category":"","description":""},{"word":"台风韦帕","word_scheme":"#台风韦帕#","num":99026,"rank":48,"category":"社会","description":"今年第六号台风“韦帕”已加强为台风级，将于20日中午到夜间正面袭击粤港澳大湾区。"},{"word":"香港地铁禁止晾脚告示","word_scheme":"香港地铁禁止晾脚告示","num":98649,"icon_desc":"新","rank":49,"category":"","description":""}]