[{"word":"东部战区进逼","word_scheme":"#东部战区进逼#","num":1172909,"icon_desc":"沸","rank":0,"category":"时事","description":"“台独”作妖，引火烧身。东部战区发布军事行动主题海报《进逼》↓↓"},{"word":"快递员因同一人连收100个包裹报警了","word_scheme":"#快递员因同一人连收100个包裹报警了#","num":618568,"rank":1,"category":"社会","description":"近日，无锡快递员李鲲鹏在派送快递时发现一收件人连续收到78个到付快递，联系收件人时对方表示等剩下的22个快递到了再一起签收。"},{"word":"国家标准住宅项目规范发布","word_scheme":"#国家标准住宅项目规范发布#","num":484232,"rank":2,"category":"社会","description":""},{"word":"小米集团午后跌超4%","word_scheme":"#小米集团午后跌超4%#","num":463164,"icon_desc":"热","rank":3,"category":"财经","description":"4月1日，小米集团午后跌超4%。"},{"word":"黄旭熙宣布台湾出道","word_scheme":"#黄旭熙宣布台湾出道#","num":444004,"icon_desc":"热","rank":4,"category":"明星-港台","description":""},{"word":"金饰价格涨到953元","word_scheme":"#金饰价格涨到953元#","num":386906,"icon_desc":"新","rank":5,"category":"财经","description":""},{"word":"利路修正式退圈","word_scheme":"#利路修正式退圈#","num":332460,"rank":6,"category":"明星-内地","description":"利路修正式退圈"},{"word":"10元盒饭姐因浪费气得不想出摊","word_scheme":"#10元盒饭姐因浪费气得不想出摊#","num":298185,"rank":7,"category":"社会","description":"3月30日，有一家八口带两名幼童就餐，在盒饭姐王荣亚的摊位前浪费餐食，对此她非常生气。"},{"word":"蓝莓便宜了","word_scheme":"#蓝莓便宜了#","num":293331,"rank":8,"category":"财经","description":""},{"word":"官方回应中学被投诉强制女生剪短发","word_scheme":"#官方回应中学被投诉强制女生剪短发#","num":292785,"icon_desc":"新","rank":9,"category":"社会","description":"近日，福建龙岩市永定区一学生家属小林（化名）向澎湃公众互动平台“服务湃”反映称，自己的妹妹在永定三中就读，被要求剪短发，否则不让去学校。"},{"word":"小米SU7高速碰撞爆燃事件细节","word_scheme":"#小米SU7高速碰撞爆燃事件细节#","num":10096225,"icon_desc":"爆","rank":10,"category":"社会","description":""},{"word":"金秀贤 迪士尼","word_scheme":"金秀贤 迪士尼","num":284308,"icon_desc":"新","rank":11,"category":"","description":""},{"word":"鹿晗站姐","word_scheme":"鹿晗站姐","num":281668,"icon_desc":"新","rank":12,"category":"","description":""},{"word":"曲曲大女人偷税被罚","word_scheme":"#曲曲大女人偷税被罚#","num":278291,"icon_desc":"新","rank":13,"category":"社会","description":"4月1日，税务部门公布5起偷逃税款被处罚案件。"},{"word":"白宫称对群聊门的调查已结束","word_scheme":"#白宫称对群聊门的调查已结束#","num":272272,"icon_desc":"新","rank":14,"category":"时事","description":"据美国媒体报道，尽管外界围绕美国“群聊门”泄密事件的疑虑仍未消散，白宫新闻秘书莱维特3月31日表示，政府关于该事件的调查已结束。"},{"word":"杨幂站姐拍的迪丽热巴","word_scheme":"#杨幂站姐拍的迪丽热巴#","num":266861,"icon_desc":"新","rank":15,"category":"明星","description":"杨幂站姐拍的迪丽热巴"},{"word":"张艺凡瘦成这样","word_scheme":"#张艺凡瘦成这样#","num":259035,"icon_desc":"热","rank":16,"category":"明星","description":""},{"word":"孙坚 我是唐嫣的兵","word_scheme":"孙坚 我是唐嫣的兵","num":249284,"icon_desc":"新","rank":17,"category":"","description":""},{"word":"悉尼妹分手","word_scheme":"#悉尼妹分手#","num":248305,"icon_desc":"新","rank":18,"category":"明星","description":""},{"word":"金价1个月每克最高涨了71元","word_scheme":"#金价1个月每克最高涨了71元#","num":247380,"icon_desc":"新","rank":19,"category":"社会","description":""},{"word":"夫妻3胎喜得女儿发10万个鸡蛋庆祝","word_scheme":"#夫妻3胎喜得女儿发10万个鸡蛋庆祝#","num":245704,"rank":20,"category":"社会","description":"近日，安徽蚌埠。一对夫妻生了2个儿子后第3胎喜得千金，高兴得请十班唢呐唱了2天，免费给村民发10万个鸡蛋。当事人张女士介绍：“我们家老大15岁，老二是8岁，然后来了一个千金，请十班唢呐唱了2天，10万个鸡蛋一个村一个村地免费发。”"},{"word":"樊振东在古茗鲜活的一天","word_scheme":"#樊振东在古茗鲜活的一天#","num":245443,"rank":21,"category":"体育","description":""},{"word":"台湾","word_scheme":"台湾","num":244465,"rank":22,"category":"社会","description":""},{"word":"愚人节站姐团建","word_scheme":"#愚人节站姐团建#","num":241965,"rank":23,"category":"明星-内地","description":"又到了站姐们愚人节一年一度的团建，快来晒出你家站姐拍的照片吧！"},{"word":"郑钦文W中文版封面人物","word_scheme":"#郑钦文W中文版封面人物#","num":235501,"icon_desc":"新","rank":24,"category":"时尚","description":""},{"word":"医生建议想减肥的人早晚分别称体重","word_scheme":"#医生建议想减肥的人早晚分别称体重#","num":231354,"icon_desc":"新","rank":25,"category":"社会","description":"据武汉市第八医院肥胖与代谢病诊疗中心医生介绍，其实，想减肥的人除了管住嘴迈开腿，还要学会科学称体重。"},{"word":"金秀贤把鼻子上的妆抹掉了","word_scheme":"#金秀贤把鼻子上的妆抹掉了#","num":220721,"rank":26,"category":"明星","description":"笑晕…"},{"word":"孟子义站姐发了李昀锐和秦霄贤","word_scheme":"#孟子义站姐发了李昀锐和秦霄贤#","num":210616,"rank":27,"category":"明星-内地","description":"4月1日，愚人节站姐团建，有网友发现孟子义站姐发了李昀锐和秦霄贤。"},{"word":"李泽锋说这次在剧里绝对不出轨","word_scheme":"李泽锋说这次在剧里绝对不出轨","num":201053,"icon_desc":"新","flag_desc":"剧集","rank":28,"category":"","description":""},{"word":"被抢婴母亲称6000万不敌17年苦","word_scheme":"被抢婴母亲称6000万不敌17年苦","num":199558,"icon_desc":"新","rank":29,"category":"社会","description":"一审开庭在即，乔守芬说，“孩子和我们都是受害人，要求对方赔偿误工费、精神损失费等600多万元。”谈及这17年的痛苦经历，乔守芬坦言，身体和心理上都受到了巨大的伤害，“常常夜里惊醒，包里随身携带治疗头痛的药品”。她说，“就算给我6000万，我都不愿意受这17年的苦！”"},{"word":"愚人节各大品牌发癫团建","word_scheme":"#愚人节各大品牌发癫团建#","num":199411,"icon_desc":"新","rank":30,"category":"搞笑","description":""},{"word":"东部战区","word_scheme":"#东部战区#","num":172581,"icon_desc":"新","rank":31,"category":"军事","description":"东部战区权威发布"},{"word":"电视剧千秋令定档","word_scheme":"#电视剧千秋令定档#","num":171260,"icon_desc":"新","flag_desc":"剧集","rank":32,"category":"电视剧","description":"张予曦、佟梦实主演电视剧《千秋令》定档4月8日，正邪交锋，宿命难逃，锁定芒果TV，敬请期待！"},{"word":"洪小铃孕肚照","word_scheme":"#洪小铃孕肚照#","num":171048,"rank":33,"category":"明星-港台","description":""},{"word":"大家好我是徐俊大","word_scheme":"#大家好我是徐俊大#","num":168262,"icon_desc":"新","rank":34,"category":"综艺","description":""},{"word":"愚人节","word_scheme":"愚人节","num":167190,"rank":35,"category":"社会","description":"四月伊始，与你同乐！祝大家愚人节快乐～"},{"word":"英雄联盟改名大乱斗联盟","word_scheme":"#英雄联盟改名大乱斗联盟#","num":162265,"rank":36,"category":"游戏","description":"欢迎来到大乱斗联盟，在版本更新后，《英雄联盟》将改名为《大乱斗联盟》"},{"word":"税务总局去年对网络主播查补收入8.99亿","word_scheme":"#税务总局去年对网络主播查补收入8.99亿#","num":150181,"rank":37,"category":"社会","description":""},{"word":"文淇谈传承与创新","word_scheme":"文淇谈传承与创新","num":143187,"rank":38,"category":"","description":""},{"word":"愚人节的AG长这样","word_scheme":"#愚人节的AG长这样#","num":141576,"icon_desc":"新","rank":39,"category":"游戏","description":"猜猜愚人节的AG银长什么样吧～"},{"word":"张本智和3比1罗伯勒斯","word_scheme":"张本智和3比1罗伯勒斯","num":140852,"icon_desc":"新","rank":40,"category":"体育","description":""},{"word":"檀健次站姐发了相柳未公开图","word_scheme":"#檀健次站姐发了相柳未公开图#","num":140683,"rank":41,"category":"电视剧","description":"檀健次站姐发了相柳未公开图，愚人节不是放刀子的节日呜呜呜！​​​"},{"word":"邓为站姐发了fx","word_scheme":"#邓为站姐发了fx#","num":134480,"rank":42,"category":"明星-日韩","description":"我们函数"},{"word":"字节招聘年限放宽","word_scheme":"#字节招聘年限放宽#","num":131984,"icon_desc":"新","rank":43,"category":"财经","description":"字节跳动近期召开内部政策会，要求招聘“突破经验依赖”，不止招经验丰富的人，也要多招毕业不久的优秀的人。"},{"word":"赴山海","word_scheme":"赴山海","num":123661,"flag_desc":"剧集","rank":44,"category":"电视剧","description":""},{"word":"北京骑手回应缴五险一金后月收入","word_scheme":"#北京骑手回应缴五险一金后月收入#","num":119802,"rank":45,"category":"社会","description":"距离外卖平台宣布为全职骑手缴纳五险一金已有一个多月。近日，记者在北京街头采访了多位骑手。记者了解到，在成为全职骑手后，北京不少骑手的单量有明显增加，月收入也有所提高。"},{"word":"夫妻自如租房5年妻子多项指标异常","word_scheme":"#夫妻自如租房5年妻子多项指标异常#","num":119660,"rank":46,"category":"社会","description":""},{"word":"缅甸地震2719人遇难","word_scheme":"#缅甸地震2719人遇难#","num":118467,"rank":47,"category":"社会","description":"总台记者当地时间4月1日获悉，缅甸强震已造成2719人遇难。"},{"word":"租客体检多处异常怀疑房子发霉所致","word_scheme":"#租客体检多处异常怀疑房子发霉所致#","num":117452,"icon_desc":"新","rank":48,"category":"社会","description":"小许两口子在一间出租房里住了五年，感觉身体不舒服就去检查，结果妻子查出一些问题，他怀疑是居住环境导致。一番检查后，小许发现房子有多处发霉..."},{"word":"公摊面积最大的蔬菜","word_scheme":"公摊面积最大的蔬菜","num":114909,"rank":49,"category":"","description":""}]