[{"word":"英国水煮遗体排入下水道或将合法化","word_scheme":"#英国水煮遗体排入下水道或将合法化#","num":1267876,"icon_desc":"热","rank":0,"category":"社会","description":"英国水煮遗体排入下水道或将合法化，美澳加部分地区有此下葬方式"},{"word":"刘诗诗用心在养labubu","word_scheme":"刘诗诗用心在养labubu","num":797474,"icon_desc":"热","rank":1,"category":"","description":""},{"word":"中非贸易规模已超2万亿元","word_scheme":"#中非贸易规模已超2万亿元#","num":728439,"icon_desc":"新","rank":2,"category":"社会","description":"海关总署6月11日发布数据显示，2000年中非合作论坛成立以来，中国对非洲进出口总值由当年不足1000亿元增至2024年2.1万亿元，累计增长超20倍，年均增速达到14.2%。"},{"word":"真相只有一个 评论来圈智搜","num":712707,"icon_desc":"官宣","rank":2,"category":"互联网","description":"智搜新上线的博文求证功能大家用上了吗？今天就来教大家通过评论获取智搜求证和解读的正确姿势！"},{"word":"歌手第五期歌单","word_scheme":"歌手第五期歌单","num":660036,"icon_desc":"新","flag_desc":"综艺","rank":3,"category":"","description":""},{"word":"曾744分考上清华的他现状","word_scheme":"#曾744分考上清华的他现状#","num":515175,"rank":4,"category":"社会","description":""},{"word":"韦东奕称已受舆论影响不想再做回应","word_scheme":"#韦东奕称已受舆论影响不想再做回应#","num":504975,"icon_desc":"新","rank":5,"category":"社会","description":""},{"word":"好博会到底有谁在啊","num":497113,"icon_desc":"荐","rank":5,"category":"财经","description":""},{"word":"樊振东无世排后击败世排第一","word_scheme":"#樊振东无世排后击败世排第一#","num":482510,"rank":6,"category":"体育","description":"2025乒超第一阶段男团，上海地产集团vs黄石基地·华新第二场，@樊振东分别以7-11、11-7、11-7、10-12、11-8战胜@林詩棟y，斩获乒超五连胜。"},{"word":"孕期出轨男子诈骗情人6万给妻女用","word_scheme":"#孕期出轨男子诈骗情人6万给妻女用#","num":443671,"rank":7,"category":"社会","description":""},{"word":"中国田间好丰景","word_scheme":"#中国田间好丰景#","num":442158,"icon_desc":"新","rank":8,"category":"财经","description":"农业农村部发布的机收进度显示，截至昨天（10日）17点，全国已收获夏粮小麦2.6亿亩，收获进度过七成。"},{"word":"警方立案调查女子眼睛遭水枪击伤","word_scheme":"#警方立案调查女子眼睛遭水枪击伤#","num":439791,"icon_desc":"新","rank":9,"category":"社会","description":"6月7日，一女子在山东省潍坊市临朐县齐鲁嵩山峡谷漂流游玩时，遭陌生男子用高压水枪冲击，导致其眼睛受伤。6月11日，现代快报记者从临朐县委宣传部获悉，目前这起事件警方已立案调查。"},{"word":"Mai官宣订婚","word_scheme":"#Mai官宣订婚#","num":438835,"icon_desc":"新","rank":10,"category":"明星-其他","description":""},{"word":"阿里离职员工内网发帖","word_scheme":"#阿里离职员工内网发帖#","num":435131,"icon_desc":"新","rank":11,"category":"财经","description":""},{"word":"马云回复离职员工发文","word_scheme":"#马云回复离职员工发文#","num":433216,"icon_desc":"新","rank":12,"category":"互联网","description":""},{"word":"女子称肾穿刺前医院未查其怀孕致引产","word_scheme":"#女子称肾穿刺前医院未查其怀孕致引产#","num":431898,"icon_desc":"新","rank":13,"category":"社会","description":"因尿蛋白异常，37岁的李女士入院进行治疗，接受了肾穿刺手术等治疗。目前虽然肾病得到缓解，却发现她已有近4个月身孕，因服用药物原因，不得不进行了引产。"},{"word":"张桂梅给毕业生写的信看泪目了","word_scheme":"#张桂梅给毕业生写的信看泪目了#","num":429127,"icon_desc":"新","rank":14,"category":"社会","description":""},{"word":"王子璇腰伤退出她的瞳拍摄","word_scheme":"#王子璇腰伤退出她的瞳拍摄#","num":427570,"icon_desc":"新","rank":15,"category":"电视剧","description":"王子璇腰伤退出她的瞳拍摄"},{"word":"韦东奕办公桌上放着熟悉的大矿泉水瓶","word_scheme":"#韦东奕办公桌上放着熟悉的大矿泉水瓶#","num":389147,"icon_desc":"新","rank":16,"category":"社会","description":""},{"word":"戚薇你快管管李承铉吧","word_scheme":"戚薇你快管管李承铉吧","num":368720,"icon_desc":"新","rank":17,"category":"","description":""},{"word":"藏海传导演说肖战确实太好看了","word_scheme":"#藏海传导演说肖战确实太好看了#","num":362262,"flag_desc":"剧集","rank":18,"category":"明星-内地","description":"随着《藏海传》的热播，肖战的演技也受到了诸多好评。"},{"word":"当地称致女孩失明的水枪非高压水枪","word_scheme":"#当地称致女孩失明的水枪非高压水枪#","num":360496,"icon_desc":"新","rank":19,"category":"社会","description":"6月11日，现代快报记者从山东临朐县委宣传部获悉，遭陌生男子用水枪冲击女孩，眼睛经过医院积极治疗恢复良好。肇事者当时持有的并非传统意义上的高压水枪，而是抽拉式玩具水枪，目前肇事者正在配合警方开展调查。"},{"word":"蜜雪冰城","word_scheme":"蜜雪冰城","num":359899,"rank":20,"category":"美食","description":"你爱我，我爱你~蜜雪冰城甜蜜蜜"},{"word":"全球唯一薄荷色labubu108万成交","word_scheme":"#全球唯一薄荷色labubu108万成交#","num":342047,"rank":21,"category":"社会","description":"6月10日，北京，一款全球唯一的薄荷色LABUBU在永乐2025春季拍卖会上亮相，落槌价为108万元，目前已结拍。"},{"word":"樊振东王楚钦今晚无缘交手","word_scheme":"#樊振东王楚钦今晚无缘交手#","num":289583,"rank":22,"category":"体育","description":""},{"word":"王楚钦说没人敢说有信心战胜樊振东","word_scheme":"#王楚钦说没人敢说有信心战胜樊振东#","num":272566,"rank":23,"category":"社会","description":"6月11日，2025乒超第一阶段男团，樊振东战胜林诗栋。据悉，山东魏桥·向尚运动队与上海地产集团队将于今晚18:00展开对决。王楚钦在之前的采访中曾坦言樊振东的强大，“任何人都不敢说有信心战胜樊振东”。经过几年磨砺，如果两人再度对决，必将是一场精彩的比赛。"},{"word":"孙颖莎所在俱乐部女子第一","word_scheme":"#孙颖莎所在俱乐部女子第一#","num":255002,"icon_desc":"新","rank":24,"category":"体育","description":"2025乒超联赛第一阶段女子团体积分排名，深圳大学排名第一。"},{"word":"肖战藏海传收官小作文","word_scheme":"#肖战藏海传收官小作文#","num":253125,"icon_desc":"新","flag_desc":"剧集","rank":25,"category":"电视剧","description":""},{"word":"被一个个大国重器飒到了","word_scheme":"#被一个个大国重器飒到了#","num":249151,"rank":26,"category":"社会","description":"三代深潜器接力逐梦深蓝，见证的不仅是大国重器的迭新，更是一群人与一片海的共同成长。"},{"word":"她的瞳","word_scheme":"她的瞳","num":247559,"icon_desc":"新","rank":27,"category":"","description":""},{"word":"又有两位艺术家不能体面的老去了","word_scheme":"又有两位艺术家不能体面的老去了","num":244365,"rank":28,"category":"","description":""},{"word":"老人摔断腿后与邻居小狗交了朋友","word_scheme":"#老人摔断腿后与邻居小狗交了朋友#","num":241369,"icon_desc":"暖","rank":29,"category":"社会","description":"6月8日，江苏徐州，老人一生喜欢养狗，摔断腿后不方便养，经常下楼找邻居家的狗狗大黄一起玩。老人与大黄头碰头的那一刻，看得人泪目。"},{"word":"女子兼职给Labubu钩衣服月入超2万","word_scheme":"#女子兼职给Labubu钩衣服月入超2万#","num":240050,"rank":30,"category":"社会","description":"女子每月给Labubu手工钩织衣服，兼职月营收超2万元，其中海外订单接近一半。"},{"word":"台湾台东5.8级地震","word_scheme":"#台湾台东5.8级地震#","num":229489,"rank":31,"category":"社会","description":"11日19时00分在台湾台东县海域（北纬23.33度，东经121.72度）发生5.8级地震，震源深度20千米。"},{"word":"无畏","word_scheme":"无畏","num":211447,"icon_desc":"新","rank":32,"category":"","description":""},{"word":"李晨晒哥斯拉labubu","word_scheme":"#李晨晒哥斯拉labubu#","num":198358,"rank":33,"category":"明星","description":""},{"word":"2025乒超联赛第一阶段积分排名","word_scheme":"#2025乒超联赛第一阶段积分排名#","num":198005,"icon_desc":"新","rank":34,"category":"体育","description":""},{"word":"女子因发量太多剃掉五分之四头发","word_scheme":"#女子因发量太多剃掉五分之四头发#","num":172889,"rank":35,"category":"社会","description":"近日，北京，一女子分享自己的苦恼称，自己因发量太多想方设法地让自己头发看起来比较轻薄，为此剃掉了五分之四的头发。"},{"word":"黄友政说能和樊振东交手非常开心","word_scheme":"#黄友政说能和樊振东交手非常开心#","num":167512,"icon_desc":"新","rank":36,"category":"体育","description":""},{"word":"汕头明润3比2山东鲁能","word_scheme":"#汕头明润3比2山东鲁能#","num":159035,"icon_desc":"新","rank":37,"category":"体育","description":"🏓️乒超联赛第一阶段男团，汕头明润3比2战胜山东鲁能"},{"word":"王楚钦梁靖崑真的很努力在憋笑了","word_scheme":"#王楚钦梁靖崑真的很努力在憋笑了#","num":156200,"icon_desc":"新","rank":38,"category":"体育","description":"6月11日，河北雄安。国乒“喜剧人”实锤，王楚钦、梁靖崑台下观战，努力憋笑中，真的是快乐乒乓啊！"},{"word":"山东魏桥乒超5连胜","word_scheme":"#山东魏桥乒超5连胜#","num":151030,"icon_desc":"新","rank":39,"category":"体育","description":"乒超第一阶段，山东魏桥·向尚运动3比0汕头明润，收获五连胜。"},{"word":"临江仙热度","word_scheme":"临江仙热度","num":150079,"icon_desc":"新","flag_desc":"剧集","rank":40,"category":"电视剧-国产剧","description":""},{"word":"蜜雪冰城含菌量超标被通报","word_scheme":"#蜜雪冰城含菌量超标被通报#","num":146087,"rank":41,"category":"社会","description":"6月9日，香港特区政府食物环境卫生署食物安全中心公布，蜜雪冰城一个冰冻甜点样本的大肠菌群含量和总含菌量超出法例上限。"},{"word":"临江仙受众","word_scheme":"临江仙受众","num":144926,"flag_desc":"剧集","rank":42,"category":"","description":""},{"word":"刘浩存进行曲","word_scheme":"刘浩存进行曲","num":144028,"icon_desc":"新","flag_desc":"剧集","rank":43,"category":"","description":""},{"word":"好好吃饭才能瘦","word_scheme":"好好吃饭才能瘦","num":133216,"rank":44,"category":"","description":""},{"word":"小黄豆回应与孙恩盛闹掰","word_scheme":"#小黄豆回应与孙恩盛闹掰#","num":128325,"icon_desc":"新","rank":45,"category":"明星","description":""},{"word":"高考完挑扁担回家的女孩想学师范","word_scheme":"#高考完挑扁担回家的女孩想学师范#","num":124506,"icon_desc":"新","rank":46,"category":"社会","description":""},{"word":"真的爱韦神就别打扰韦东奕","word_scheme":"#真的爱韦神就别打扰韦东奕#","num":123348,"icon_desc":"新","rank":47,"category":"社会","description":""},{"word":"马斯克深夜反悔","word_scheme":"#马斯克深夜反悔#","num":122481,"icon_desc":"新","rank":48,"category":"社会","description":"美东时间11日凌晨，埃隆·马斯克在其社交媒体平台“X”上表示，他对上周发表的一些关于美国总统特朗普的帖子感到后悔，称“内容说得太过了”。"},{"word":"如果你感觉自己莫名其妙很累","word_scheme":"#如果你感觉自己莫名其妙很累#","num":118195,"icon_desc":"新","rank":49,"category":"情感","description":"如果你感觉自己莫名其妙很累"}]